{"meta":{"app":"https://www.codeandweb.com/texturepacker","version":"3.0","smartupdate":"$TexturePacker:SmartUpdate:80a090ea1b336a7e971a10346888cf5c:30d92424c9e4f4fd607939ac9a541a8d:5629b26afc552af823f9b766593fb970$","image":"asset.webp","format":"RGBA8888","size":{"w":1016,"h":1240},"scale":"1"},"frames":{"4886/1_1":{"rotated":false,"trimmed":true,"sourceSize":{"w":400,"h":400},"spriteSourceSize":{"x":162,"y":147,"w":76,"h":61},"frame":{"x":803,"y":1,"w":76,"h":61}},"4886/2_1":{"rotated":false,"trimmed":true,"sourceSize":{"w":400,"h":400},"spriteSourceSize":{"x":173,"y":145,"w":64,"h":64},"frame":{"x":1,"y":383,"w":64,"h":64}},"4886/3_1":{"rotated":false,"trimmed":true,"sourceSize":{"w":400,"h":400},"spriteSourceSize":{"x":177,"y":147,"w":55,"h":70},"frame":{"x":546,"y":939,"w":55,"h":70}},"4886/4_1":{"rotated":false,"trimmed":true,"sourceSize":{"w":400,"h":400},"spriteSourceSize":{"x":172,"y":151,"w":63,"h":66},"frame":{"x":909,"y":599,"w":63,"h":66}},"4886/5_1":{"rotated":false,"trimmed":true,"sourceSize":{"w":400,"h":400},"spriteSourceSize":{"x":162,"y":157,"w":76,"h":62},"frame":{"x":347,"y":189,"w":76,"h":62}},"4886/6_1":{"rotated":false,"trimmed":true,"sourceSize":{"w":400,"h":400},"spriteSourceSize":{"x":165,"y":151,"w":64,"h":66},"frame":{"x":1,"y":651,"w":64,"h":66}},"4886/7_1":{"rotated":false,"trimmed":true,"sourceSize":{"w":400,"h":400},"spriteSourceSize":{"x":168,"y":147,"w":55,"h":71},"frame":{"x":72,"y":1075,"w":55,"h":71}},"4886/8_1":{"rotated":false,"trimmed":true,"sourceSize":{"w":400,"h":400},"spriteSourceSize":{"x":162,"y":145,"w":64,"h":64},"frame":{"x":66,"y":449,"w":64,"h":64}},"4886/9_1":{"rotated":false,"trimmed":true,"sourceSize":{"w":400,"h":400},"spriteSourceSize":{"x":160,"y":145,"w":75,"h":64},"frame":{"x":132,"y":449,"w":75,"h":64}},"4886/9_2":{"rotated":false,"trimmed":true,"sourceSize":{"w":400,"h":400},"spriteSourceSize":{"x":160,"y":146,"w":75,"h":63},"frame":{"x":228,"y":318,"w":75,"h":63}},"4886/9_3":{"rotated":false,"trimmed":true,"sourceSize":{"w":400,"h":400},"spriteSourceSize":{"x":160,"y":146,"w":75,"h":62},"frame":{"x":425,"y":189,"w":75,"h":62}},"4886/9_4":{"rotated":false,"trimmed":true,"sourceSize":{"w":400,"h":400},"spriteSourceSize":{"x":162,"y":147,"w":75,"h":61},"frame":{"x":377,"y":62,"w":75,"h":61}},"4886/9_5":{"rotated":false,"trimmed":true,"sourceSize":{"w":400,"h":400},"spriteSourceSize":{"x":165,"y":145,"w":73,"h":64},"frame":{"x":209,"y":449,"w":73,"h":64}},"4886/9_6":{"rotated":false,"trimmed":true,"sourceSize":{"w":400,"h":400},"spriteSourceSize":{"x":164,"y":146,"w":74,"h":63},"frame":{"x":305,"y":318,"w":74,"h":63}},"4886/9_7":{"rotated":false,"trimmed":true,"sourceSize":{"w":400,"h":400},"spriteSourceSize":{"x":164,"y":146,"w":75,"h":62},"frame":{"x":502,"y":190,"w":75,"h":62}},"4886/9_8":{"rotated":false,"trimmed":true,"sourceSize":{"w":400,"h":400},"spriteSourceSize":{"x":162,"y":147,"w":75,"h":61},"frame":{"x":454,"y":62,"w":75,"h":61}},"4886/10_1":{"rotated":false,"trimmed":true,"sourceSize":{"w":400,"h":400},"spriteSourceSize":{"x":166,"y":149,"w":73,"h":62},"frame":{"x":531,"y":62,"w":73,"h":62}},"4886/10_2":{"rotated":false,"trimmed":true,"sourceSize":{"w":400,"h":400},"spriteSourceSize":{"x":167,"y":148,"w":71,"h":62},"frame":{"x":606,"y":63,"w":71,"h":62}},"4886/10_3":{"rotated":false,"trimmed":true,"sourceSize":{"w":400,"h":400},"spriteSourceSize":{"x":169,"y":147,"w":67,"h":63},"frame":{"x":579,"y":191,"w":67,"h":63}},"4886/10_4":{"rotated":false,"trimmed":true,"sourceSize":{"w":400,"h":400},"spriteSourceSize":{"x":173,"y":146,"w":58,"h":66},"frame":{"x":761,"y":461,"w":58,"h":66}},"4886/10_5":{"rotated":false,"trimmed":true,"sourceSize":{"w":400,"h":400},"spriteSourceSize":{"x":174,"y":146,"w":55,"h":69},"frame":{"x":621,"y":726,"w":55,"h":69}},"4886/10_6":{"rotated":false,"trimmed":true,"sourceSize":{"w":400,"h":400},"spriteSourceSize":{"x":173,"y":146,"w":57,"h":69},"frame":{"x":605,"y":797,"w":57,"h":69}},"4886/10_7":{"rotated":false,"trimmed":true,"sourceSize":{"w":400,"h":400},"spriteSourceSize":{"x":174,"y":147,"w":59,"h":66},"frame":{"x":821,"y":462,"w":59,"h":66}},"4886/10_8":{"rotated":false,"trimmed":true,"sourceSize":{"w":400,"h":400},"spriteSourceSize":{"x":169,"y":148,"w":69,"h":63},"frame":{"x":648,"y":192,"w":69,"h":63}},"4886/11_1":{"rotated":false,"trimmed":true,"sourceSize":{"w":400,"h":400},"spriteSourceSize":{"x":177,"y":148,"w":58,"h":67},"frame":{"x":67,"y":651,"w":58,"h":67}},"4886/11_2":{"rotated":false,"trimmed":true,"sourceSize":{"w":400,"h":400},"spriteSourceSize":{"x":177,"y":147,"w":56,"h":68},"frame":{"x":503,"y":726,"w":56,"h":68}},"4886/11_3":{"rotated":false,"trimmed":true,"sourceSize":{"w":400,"h":400},"spriteSourceSize":{"x":177,"y":145,"w":56,"h":69},"frame":{"x":664,"y":804,"w":56,"h":69}},"4886/11_4":{"rotated":false,"trimmed":true,"sourceSize":{"w":400,"h":400},"spriteSourceSize":{"x":177,"y":145,"w":56,"h":71},"frame":{"x":542,"y":1011,"w":56,"h":71}},"4886/11_5":{"rotated":false,"trimmed":true,"sourceSize":{"w":400,"h":400},"spriteSourceSize":{"x":176,"y":148,"w":58,"h":68},"frame":{"x":561,"y":726,"w":58,"h":68}},"4886/11_6":{"rotated":false,"trimmed":true,"sourceSize":{"w":400,"h":400},"spriteSourceSize":{"x":176,"y":147,"w":57,"h":71},"frame":{"x":600,"y":1018,"w":57,"h":71}},"4886/11_7":{"rotated":false,"trimmed":true,"sourceSize":{"w":400,"h":400},"spriteSourceSize":{"x":177,"y":148,"w":56,"h":71},"frame":{"x":659,"y":1019,"w":56,"h":71}},"4886/11_8":{"rotated":false,"trimmed":true,"sourceSize":{"w":400,"h":400},"spriteSourceSize":{"x":177,"y":147,"w":57,"h":71},"frame":{"x":717,"y":1020,"w":57,"h":71}},"4886/12_1":{"rotated":false,"trimmed":true,"sourceSize":{"w":400,"h":400},"spriteSourceSize":{"x":178,"y":148,"w":56,"h":71},"frame":{"x":776,"y":1020,"w":56,"h":71}},"4886/12_2":{"rotated":false,"trimmed":true,"sourceSize":{"w":400,"h":400},"spriteSourceSize":{"x":178,"y":148,"w":57,"h":70},"frame":{"x":245,"y":933,"w":57,"h":70}},"4886/12_3":{"rotated":false,"trimmed":true,"sourceSize":{"w":400,"h":400},"spriteSourceSize":{"x":179,"y":149,"w":56,"h":68},"frame":{"x":678,"y":734,"w":56,"h":68}},"4886/12_4":{"rotated":false,"trimmed":true,"sourceSize":{"w":400,"h":400},"spriteSourceSize":{"x":172,"y":151,"w":69,"h":64},"frame":{"x":946,"y":264,"w":69,"h":64}},"4886/12_5":{"rotated":false,"trimmed":true,"sourceSize":{"w":400,"h":400},"spriteSourceSize":{"x":168,"y":153,"w":74,"h":62},"frame":{"x":679,"y":64,"w":74,"h":62}},"4886/12_6":{"rotated":false,"trimmed":true,"sourceSize":{"w":400,"h":400},"spriteSourceSize":{"x":170,"y":152,"w":71,"h":64},"frame":{"x":381,"y":318,"w":71,"h":64}},"4886/12_7":{"rotated":false,"trimmed":true,"sourceSize":{"w":400,"h":400},"spriteSourceSize":{"x":170,"y":152,"w":70,"h":65},"frame":{"x":471,"y":453,"w":70,"h":65}},"4886/12_8":{"rotated":false,"trimmed":true,"sourceSize":{"w":400,"h":400},"spriteSourceSize":{"x":178,"y":150,"w":56,"h":69},"frame":{"x":722,"y":805,"w":56,"h":69}},"4886/13_1":{"rotated":false,"trimmed":true,"sourceSize":{"w":400,"h":400},"spriteSourceSize":{"x":162,"y":155,"w":75,"h":66},"frame":{"x":882,"y":462,"w":75,"h":66}},"4886/13_2":{"rotated":false,"trimmed":true,"sourceSize":{"w":400,"h":400},"spriteSourceSize":{"x":163,"y":157,"w":75,"h":63},"frame":{"x":719,"y":192,"w":75,"h":63}},"4886/13_3":{"rotated":false,"trimmed":true,"sourceSize":{"w":400,"h":400},"spriteSourceSize":{"x":163,"y":158,"w":75,"h":62},"frame":{"x":755,"y":64,"w":75,"h":62}},"4886/13_4":{"rotated":false,"trimmed":true,"sourceSize":{"w":400,"h":400},"spriteSourceSize":{"x":162,"y":157,"w":76,"h":63},"frame":{"x":796,"y":192,"w":76,"h":63}},"4886/13_5":{"rotated":false,"trimmed":true,"sourceSize":{"w":400,"h":400},"spriteSourceSize":{"x":163,"y":156,"w":73,"h":64},"frame":{"x":454,"y":319,"w":73,"h":64}},"4886/13_6":{"rotated":false,"trimmed":true,"sourceSize":{"w":400,"h":400},"spriteSourceSize":{"x":161,"y":157,"w":75,"h":63},"frame":{"x":874,"y":199,"w":75,"h":63}},"4886/13_7":{"rotated":false,"trimmed":true,"sourceSize":{"w":400,"h":400},"spriteSourceSize":{"x":161,"y":158,"w":75,"h":62},"frame":{"x":832,"y":64,"w":75,"h":62}},"4886/13_8":{"rotated":false,"trimmed":true,"sourceSize":{"w":400,"h":400},"spriteSourceSize":{"x":161,"y":157,"w":76,"h":64},"frame":{"x":529,"y":321,"w":76,"h":64}},"4886/14_1":{"rotated":false,"trimmed":true,"sourceSize":{"w":400,"h":400},"spriteSourceSize":{"x":168,"y":150,"w":55,"h":70},"frame":{"x":127,"y":930,"w":55,"h":70}},"4886/14_2":{"rotated":false,"trimmed":true,"sourceSize":{"w":400,"h":400},"spriteSourceSize":{"x":167,"y":150,"w":56,"h":70},"frame":{"x":304,"y":933,"w":56,"h":70}},"4886/14_3":{"rotated":false,"trimmed":true,"sourceSize":{"w":400,"h":400},"spriteSourceSize":{"x":166,"y":151,"w":56,"h":68},"frame":{"x":736,"y":735,"w":56,"h":68}},"4886/14_4":{"rotated":false,"trimmed":true,"sourceSize":{"w":400,"h":400},"spriteSourceSize":{"x":160,"y":153,"w":69,"h":64},"frame":{"x":607,"y":322,"w":69,"h":64}},"4886/14_5":{"rotated":false,"trimmed":true,"sourceSize":{"w":400,"h":400},"spriteSourceSize":{"x":159,"y":154,"w":74,"h":63},"frame":{"x":1,"y":253,"w":74,"h":63}},"4886/14_6":{"rotated":false,"trimmed":true,"sourceSize":{"w":400,"h":400},"spriteSourceSize":{"x":160,"y":154,"w":71,"h":64},"frame":{"x":678,"y":322,"w":71,"h":64}},"4886/14_7":{"rotated":false,"trimmed":true,"sourceSize":{"w":400,"h":400},"spriteSourceSize":{"x":162,"y":153,"w":68,"h":66},"frame":{"x":1,"y":515,"w":68,"h":66}},"4886/14_8":{"rotated":false,"trimmed":true,"sourceSize":{"w":400,"h":400},"spriteSourceSize":{"x":167,"y":151,"w":57,"h":69},"frame":{"x":780,"y":806,"w":57,"h":69}},"4886/15_1":{"rotated":false,"trimmed":true,"sourceSize":{"w":400,"h":400},"spriteSourceSize":{"x":165,"y":149,"w":57,"h":66},"frame":{"x":284,"y":449,"w":57,"h":66}},"4886/15_2":{"rotated":false,"trimmed":true,"sourceSize":{"w":400,"h":400},"spriteSourceSize":{"x":166,"y":147,"w":57,"h":69},"frame":{"x":839,"y":806,"w":57,"h":69}},"4886/15_3":{"rotated":false,"trimmed":true,"sourceSize":{"w":400,"h":400},"spriteSourceSize":{"x":166,"y":146,"w":56,"h":69},"frame":{"x":898,"y":806,"w":56,"h":69}},"4886/15_4":{"rotated":false,"trimmed":true,"sourceSize":{"w":400,"h":400},"spriteSourceSize":{"x":166,"y":146,"w":56,"h":71},"frame":{"x":834,"y":1020,"w":56,"h":71}},"4886/15_5":{"rotated":false,"trimmed":true,"sourceSize":{"w":400,"h":400},"spriteSourceSize":{"x":166,"y":148,"w":57,"h":69},"frame":{"x":956,"y":806,"w":57,"h":69}},"4886/15_6":{"rotated":false,"trimmed":true,"sourceSize":{"w":400,"h":400},"spriteSourceSize":{"x":166,"y":148,"w":57,"h":71},"frame":{"x":892,"y":1020,"w":57,"h":71}},"4886/15_7":{"rotated":false,"trimmed":true,"sourceSize":{"w":400,"h":400},"spriteSourceSize":{"x":167,"y":148,"w":56,"h":72},"frame":{"x":129,"y":1075,"w":56,"h":72}},"4886/15_8":{"rotated":false,"trimmed":true,"sourceSize":{"w":400,"h":400},"spriteSourceSize":{"x":166,"y":148,"w":57,"h":70},"frame":{"x":362,"y":936,"w":57,"h":70}},"4886/16_1":{"rotated":false,"trimmed":true,"sourceSize":{"w":400,"h":400},"spriteSourceSize":{"x":159,"y":149,"w":74,"h":62},"frame":{"x":909,"y":71,"w":74,"h":62}},"4886/16_2":{"rotated":false,"trimmed":true,"sourceSize":{"w":400,"h":400},"spriteSourceSize":{"x":161,"y":148,"w":71,"h":62},"frame":{"x":1,"y":125,"w":71,"h":62}},"4886/16_3":{"rotated":false,"trimmed":true,"sourceSize":{"w":400,"h":400},"spriteSourceSize":{"x":162,"y":147,"w":68,"h":63},"frame":{"x":77,"y":253,"w":68,"h":63}},"4886/16_4":{"rotated":false,"trimmed":true,"sourceSize":{"w":400,"h":400},"spriteSourceSize":{"x":167,"y":145,"w":58,"h":67},"frame":{"x":127,"y":651,"w":58,"h":67}},"4886/16_5":{"rotated":false,"trimmed":true,"sourceSize":{"w":400,"h":400},"spriteSourceSize":{"x":170,"y":146,"w":55,"h":69},"frame":{"x":1,"y":858,"w":55,"h":69}},"4886/16_6":{"rotated":false,"trimmed":true,"sourceSize":{"w":400,"h":400},"spriteSourceSize":{"x":169,"y":146,"w":57,"h":68},"frame":{"x":794,"y":736,"w":57,"h":68}},"4886/16_7":{"rotated":false,"trimmed":true,"sourceSize":{"w":400,"h":400},"spriteSourceSize":{"x":165,"y":147,"w":60,"h":66},"frame":{"x":71,"y":515,"w":60,"h":66}},"4886/16_8":{"rotated":false,"trimmed":true,"sourceSize":{"w":400,"h":400},"spriteSourceSize":{"x":161,"y":149,"w":69,"h":62},"frame":{"x":74,"y":125,"w":69,"h":62}},"4886/17_1":{"rotated":false,"trimmed":true,"sourceSize":{"w":400,"h":400},"spriteSourceSize":{"x":164,"y":155,"w":74,"h":60},"frame":{"x":662,"y":1,"w":74,"h":60}},"4886/18_1":{"rotated":false,"trimmed":true,"sourceSize":{"w":400,"h":400},"spriteSourceSize":{"x":170,"y":153,"w":63,"h":61},"frame":{"x":738,"y":1,"w":63,"h":61}},"4886/19_1":{"rotated":false,"trimmed":true,"sourceSize":{"w":400,"h":400},"spriteSourceSize":{"x":174,"y":151,"w":54,"h":70},"frame":{"x":421,"y":937,"w":54,"h":70}},"4886/20_1":{"rotated":false,"trimmed":true,"sourceSize":{"w":400,"h":400},"spriteSourceSize":{"x":169,"y":154,"w":64,"h":66},"frame":{"x":133,"y":515,"w":64,"h":66}},"4886/21_1":{"rotated":false,"trimmed":true,"sourceSize":{"w":400,"h":400},"spriteSourceSize":{"x":162,"y":158,"w":77,"h":61},"frame":{"x":881,"y":1,"w":77,"h":61}},"4886/22_1":{"rotated":false,"trimmed":true,"sourceSize":{"w":400,"h":400},"spriteSourceSize":{"x":168,"y":153,"w":64,"h":66},"frame":{"x":199,"y":515,"w":64,"h":66}},"4886/23_1":{"rotated":false,"trimmed":true,"sourceSize":{"w":400,"h":400},"spriteSourceSize":{"x":173,"y":152,"w":54,"h":69},"frame":{"x":58,"y":859,"w":54,"h":69}},"4886/24_1":{"rotated":false,"trimmed":true,"sourceSize":{"w":400,"h":400},"spriteSourceSize":{"x":165,"y":153,"w":63,"h":61},"frame":{"x":1,"y":62,"w":63,"h":61}},"4886/25_1":{"rotated":false,"trimmed":true,"sourceSize":{"w":400,"h":400},"spriteSourceSize":{"x":162,"y":147,"w":77,"h":61},"frame":{"x":66,"y":62,"w":77,"h":61}},"4886/25_2":{"rotated":false,"trimmed":true,"sourceSize":{"w":400,"h":400},"spriteSourceSize":{"x":161,"y":146,"w":76,"h":62},"frame":{"x":145,"y":125,"w":76,"h":62}},"4886/25_3":{"rotated":false,"trimmed":true,"sourceSize":{"w":400,"h":400},"spriteSourceSize":{"x":160,"y":145,"w":90,"h":63},"frame":{"x":147,"y":253,"w":90,"h":63}},"4886/25_4":{"rotated":false,"trimmed":true,"sourceSize":{"w":400,"h":400},"spriteSourceSize":{"x":159,"y":135,"w":93,"h":73},"frame":{"x":723,"y":1093,"w":93,"h":73}},"4886/25_5":{"rotated":false,"trimmed":true,"sourceSize":{"w":400,"h":400},"spriteSourceSize":{"x":160,"y":142,"w":82,"h":66},"frame":{"x":350,"y":518,"w":82,"h":66}},"4886/25_6":{"rotated":false,"trimmed":true,"sourceSize":{"w":400,"h":400},"spriteSourceSize":{"x":160,"y":141,"w":80,"h":67},"frame":{"x":253,"y":653,"w":80,"h":67}},"4886/25_7":{"rotated":false,"trimmed":true,"sourceSize":{"w":400,"h":400},"spriteSourceSize":{"x":160,"y":141,"w":80,"h":67},"frame":{"x":253,"y":653,"w":80,"h":67}},"4886/25_8":{"rotated":false,"trimmed":true,"sourceSize":{"w":400,"h":400},"spriteSourceSize":{"x":160,"y":142,"w":80,"h":66},"frame":{"x":434,"y":520,"w":80,"h":66}},"4886/25_9":{"rotated":false,"trimmed":true,"sourceSize":{"w":400,"h":400},"spriteSourceSize":{"x":160,"y":142,"w":82,"h":66},"frame":{"x":516,"y":521,"w":82,"h":66}},"4886/25_10":{"rotated":false,"trimmed":true,"sourceSize":{"w":400,"h":400},"spriteSourceSize":{"x":160,"y":142,"w":83,"h":66},"frame":{"x":265,"y":517,"w":83,"h":66}},"4886/25_11":{"rotated":false,"trimmed":true,"sourceSize":{"w":400,"h":400},"spriteSourceSize":{"x":160,"y":142,"w":83,"h":66},"frame":{"x":265,"y":517,"w":83,"h":66}},"4886/25_12":{"rotated":false,"trimmed":true,"sourceSize":{"w":400,"h":400},"spriteSourceSize":{"x":160,"y":141,"w":80,"h":67},"frame":{"x":253,"y":653,"w":80,"h":67}},"4886/26_1":{"rotated":false,"trimmed":true,"sourceSize":{"w":400,"h":400},"spriteSourceSize":{"x":162,"y":147,"w":76,"h":61},"frame":{"x":145,"y":62,"w":76,"h":61}},"4886/26_2":{"rotated":false,"trimmed":true,"sourceSize":{"w":400,"h":400},"spriteSourceSize":{"x":162,"y":147,"w":76,"h":61},"frame":{"x":145,"y":62,"w":76,"h":61}},"4886/26_3":{"rotated":false,"trimmed":true,"sourceSize":{"w":400,"h":400},"spriteSourceSize":{"x":162,"y":147,"w":76,"h":61},"frame":{"x":145,"y":62,"w":76,"h":61}},"4886/26_4":{"rotated":false,"trimmed":true,"sourceSize":{"w":400,"h":400},"spriteSourceSize":{"x":162,"y":147,"w":76,"h":61},"frame":{"x":145,"y":62,"w":76,"h":61}},"4886/26_5":{"rotated":false,"trimmed":true,"sourceSize":{"w":400,"h":400},"spriteSourceSize":{"x":156,"y":152,"w":74,"h":64},"frame":{"x":133,"y":383,"w":74,"h":64}},"4886/26_6":{"rotated":false,"trimmed":true,"sourceSize":{"w":400,"h":400},"spriteSourceSize":{"x":156,"y":152,"w":74,"h":64},"frame":{"x":133,"y":383,"w":74,"h":64}},"4886/26_7":{"rotated":false,"trimmed":true,"sourceSize":{"w":400,"h":400},"spriteSourceSize":{"x":156,"y":152,"w":74,"h":64},"frame":{"x":133,"y":383,"w":74,"h":64}},"4886/26_8":{"rotated":false,"trimmed":true,"sourceSize":{"w":400,"h":400},"spriteSourceSize":{"x":156,"y":152,"w":74,"h":64},"frame":{"x":133,"y":383,"w":74,"h":64}},"4886/26_9":{"rotated":false,"trimmed":true,"sourceSize":{"w":400,"h":400},"spriteSourceSize":{"x":162,"y":147,"w":76,"h":61},"frame":{"x":145,"y":62,"w":76,"h":61}},"4886/26_10":{"rotated":false,"trimmed":true,"sourceSize":{"w":400,"h":400},"spriteSourceSize":{"x":162,"y":147,"w":76,"h":61},"frame":{"x":145,"y":62,"w":76,"h":61}},"4886/26_11":{"rotated":false,"trimmed":true,"sourceSize":{"w":400,"h":400},"spriteSourceSize":{"x":162,"y":147,"w":76,"h":61},"frame":{"x":145,"y":62,"w":76,"h":61}},"4886/26_12":{"rotated":false,"trimmed":true,"sourceSize":{"w":400,"h":400},"spriteSourceSize":{"x":170,"y":152,"w":73,"h":64},"frame":{"x":751,"y":322,"w":73,"h":64}},"4886/26_13":{"rotated":false,"trimmed":true,"sourceSize":{"w":400,"h":400},"spriteSourceSize":{"x":170,"y":152,"w":73,"h":64},"frame":{"x":751,"y":322,"w":73,"h":64}},"4886/26_14":{"rotated":false,"trimmed":true,"sourceSize":{"w":400,"h":400},"spriteSourceSize":{"x":170,"y":152,"w":73,"h":64},"frame":{"x":751,"y":322,"w":73,"h":64}},"4886/26_15":{"rotated":false,"trimmed":true,"sourceSize":{"w":400,"h":400},"spriteSourceSize":{"x":170,"y":152,"w":73,"h":64},"frame":{"x":751,"y":322,"w":73,"h":64}},"4886/26_16":{"rotated":false,"trimmed":true,"sourceSize":{"w":400,"h":400},"spriteSourceSize":{"x":162,"y":147,"w":76,"h":61},"frame":{"x":145,"y":62,"w":76,"h":61}},"4886/26_17":{"rotated":false,"trimmed":true,"sourceSize":{"w":400,"h":400},"spriteSourceSize":{"x":162,"y":147,"w":76,"h":61},"frame":{"x":145,"y":62,"w":76,"h":61}},"4886/26_18":{"rotated":false,"trimmed":true,"sourceSize":{"w":400,"h":400},"spriteSourceSize":{"x":162,"y":147,"w":76,"h":61},"frame":{"x":145,"y":62,"w":76,"h":61}},"4886/26_19":{"rotated":false,"trimmed":true,"sourceSize":{"w":400,"h":400},"spriteSourceSize":{"x":175,"y":146,"w":64,"h":64},"frame":{"x":1,"y":383,"w":64,"h":64}},"4886/26_20":{"rotated":false,"trimmed":true,"sourceSize":{"w":400,"h":400},"spriteSourceSize":{"x":178,"y":145,"w":55,"h":70},"frame":{"x":546,"y":939,"w":55,"h":70}},"4886/26_21":{"rotated":false,"trimmed":true,"sourceSize":{"w":400,"h":400},"spriteSourceSize":{"x":173,"y":150,"w":64,"h":66},"frame":{"x":684,"y":521,"w":64,"h":66}},"4886/26_22":{"rotated":false,"trimmed":true,"sourceSize":{"w":400,"h":400},"spriteSourceSize":{"x":164,"y":155,"w":76,"h":61},"frame":{"x":299,"y":62,"w":76,"h":61}},"4886/26_23":{"rotated":false,"trimmed":true,"sourceSize":{"w":400,"h":400},"spriteSourceSize":{"x":164,"y":155,"w":76,"h":61},"frame":{"x":299,"y":62,"w":76,"h":61}},"4886/26_24":{"rotated":false,"trimmed":true,"sourceSize":{"w":400,"h":400},"spriteSourceSize":{"x":164,"y":155,"w":76,"h":61},"frame":{"x":299,"y":62,"w":76,"h":61}},"4886/26_25":{"rotated":false,"trimmed":true,"sourceSize":{"w":400,"h":400},"spriteSourceSize":{"x":163,"y":151,"w":74,"h":65},"frame":{"x":543,"y":454,"w":74,"h":65}},"4886/26_26":{"rotated":false,"trimmed":true,"sourceSize":{"w":400,"h":400},"spriteSourceSize":{"x":163,"y":151,"w":74,"h":65},"frame":{"x":543,"y":454,"w":74,"h":65}},"4886/26_27":{"rotated":false,"trimmed":true,"sourceSize":{"w":400,"h":400},"spriteSourceSize":{"x":163,"y":151,"w":74,"h":65},"frame":{"x":543,"y":454,"w":74,"h":65}},"4886/26_28":{"rotated":false,"trimmed":true,"sourceSize":{"w":400,"h":400},"spriteSourceSize":{"x":163,"y":151,"w":74,"h":65},"frame":{"x":543,"y":454,"w":74,"h":65}},"4886/26_29":{"rotated":false,"trimmed":true,"sourceSize":{"w":400,"h":400},"spriteSourceSize":{"x":164,"y":155,"w":76,"h":61},"frame":{"x":299,"y":62,"w":76,"h":61}},"4886/26_30":{"rotated":false,"trimmed":true,"sourceSize":{"w":400,"h":400},"spriteSourceSize":{"x":164,"y":155,"w":76,"h":61},"frame":{"x":299,"y":62,"w":76,"h":61}},"4886/26_31":{"rotated":false,"trimmed":true,"sourceSize":{"w":400,"h":400},"spriteSourceSize":{"x":164,"y":155,"w":76,"h":61},"frame":{"x":299,"y":62,"w":76,"h":61}},"4886/26_32":{"rotated":false,"trimmed":true,"sourceSize":{"w":400,"h":400},"spriteSourceSize":{"x":164,"y":151,"w":74,"h":65},"frame":{"x":619,"y":454,"w":74,"h":65}},"4886/26_33":{"rotated":false,"trimmed":true,"sourceSize":{"w":400,"h":400},"spriteSourceSize":{"x":164,"y":151,"w":74,"h":65},"frame":{"x":619,"y":454,"w":74,"h":65}},"4886/26_34":{"rotated":false,"trimmed":true,"sourceSize":{"w":400,"h":400},"spriteSourceSize":{"x":164,"y":151,"w":74,"h":65},"frame":{"x":619,"y":454,"w":74,"h":65}},"4886/26_35":{"rotated":false,"trimmed":true,"sourceSize":{"w":400,"h":400},"spriteSourceSize":{"x":164,"y":151,"w":74,"h":65},"frame":{"x":619,"y":454,"w":74,"h":65}},"4886/26_36":{"rotated":false,"trimmed":true,"sourceSize":{"w":400,"h":400},"spriteSourceSize":{"x":164,"y":155,"w":76,"h":61},"frame":{"x":299,"y":62,"w":76,"h":61}},"4886/26_37":{"rotated":false,"trimmed":true,"sourceSize":{"w":400,"h":400},"spriteSourceSize":{"x":164,"y":155,"w":76,"h":61},"frame":{"x":299,"y":62,"w":76,"h":61}},"4886/26_38":{"rotated":false,"trimmed":true,"sourceSize":{"w":400,"h":400},"spriteSourceSize":{"x":164,"y":155,"w":76,"h":61},"frame":{"x":299,"y":62,"w":76,"h":61}},"4886/26_39":{"rotated":false,"trimmed":true,"sourceSize":{"w":400,"h":400},"spriteSourceSize":{"x":167,"y":149,"w":63,"h":66},"frame":{"x":750,"y":529,"w":63,"h":66}},"4886/26_40":{"rotated":false,"trimmed":true,"sourceSize":{"w":400,"h":400},"spriteSourceSize":{"x":168,"y":145,"w":55,"h":70},"frame":{"x":603,"y":946,"w":55,"h":70}},"4886/26_41":{"rotated":false,"trimmed":true,"sourceSize":{"w":400,"h":400},"spriteSourceSize":{"x":164,"y":147,"w":64,"h":64},"frame":{"x":67,"y":383,"w":64,"h":64}},"4886/26_42":{"rotated":false,"trimmed":true,"sourceSize":{"w":400,"h":400},"spriteSourceSize":{"x":162,"y":147,"w":76,"h":61},"frame":{"x":145,"y":62,"w":76,"h":61}},"4886/26_43":{"rotated":false,"trimmed":true,"sourceSize":{"w":400,"h":400},"spriteSourceSize":{"x":162,"y":147,"w":76,"h":61},"frame":{"x":145,"y":62,"w":76,"h":61}},"4886/26_44":{"rotated":false,"trimmed":true,"sourceSize":{"w":400,"h":400},"spriteSourceSize":{"x":162,"y":147,"w":76,"h":61},"frame":{"x":145,"y":62,"w":76,"h":61}},"4886/26_45":{"rotated":false,"trimmed":true,"sourceSize":{"w":400,"h":400},"spriteSourceSize":{"x":162,"y":147,"w":76,"h":61},"frame":{"x":145,"y":62,"w":76,"h":61}},"4886/26_46":{"rotated":false,"trimmed":true,"sourceSize":{"w":400,"h":400},"spriteSourceSize":{"x":165,"y":147,"w":67,"h":63},"frame":{"x":423,"y":253,"w":67,"h":63}},"4886/26_47":{"rotated":false,"trimmed":true,"sourceSize":{"w":400,"h":400},"spriteSourceSize":{"x":166,"y":146,"w":61,"h":63},"frame":{"x":951,"y":199,"w":61,"h":63}},"4886/26_48":{"rotated":false,"trimmed":true,"sourceSize":{"w":400,"h":400},"spriteSourceSize":{"x":166,"y":145,"w":59,"h":63},"frame":{"x":492,"y":254,"w":59,"h":63}},"4886/26_49":{"rotated":false,"trimmed":true,"sourceSize":{"w":400,"h":400},"spriteSourceSize":{"x":167,"y":143,"w":59,"h":64},"frame":{"x":955,"y":330,"w":59,"h":64}},"4886/26_50":{"rotated":false,"trimmed":true,"sourceSize":{"w":400,"h":400},"spriteSourceSize":{"x":168,"y":143,"w":59,"h":63},"frame":{"x":553,"y":256,"w":59,"h":63}},"4886/26_51":{"rotated":false,"trimmed":true,"sourceSize":{"w":400,"h":400},"spriteSourceSize":{"x":170,"y":143,"w":59,"h":63},"frame":{"x":614,"y":257,"w":59,"h":63}},"4886/26_52":{"rotated":false,"trimmed":true,"sourceSize":{"w":400,"h":400},"spriteSourceSize":{"x":171,"y":144,"w":59,"h":62},"frame":{"x":379,"y":125,"w":59,"h":62}},"4886/26_53":{"rotated":false,"trimmed":true,"sourceSize":{"w":400,"h":400},"spriteSourceSize":{"x":173,"y":143,"w":61,"h":63},"frame":{"x":675,"y":257,"w":61,"h":63}},"4886/26_54":{"rotated":false,"trimmed":true,"sourceSize":{"w":400,"h":400},"spriteSourceSize":{"x":174,"y":143,"w":65,"h":63},"frame":{"x":738,"y":257,"w":65,"h":63}},"4886/26_55":{"rotated":false,"trimmed":true,"sourceSize":{"w":400,"h":400},"spriteSourceSize":{"x":174,"y":143,"w":69,"h":64},"frame":{"x":209,"y":383,"w":69,"h":64}},"4886/26_56":{"rotated":false,"trimmed":true,"sourceSize":{"w":400,"h":400},"spriteSourceSize":{"x":173,"y":145,"w":73,"h":63},"frame":{"x":871,"y":264,"w":73,"h":63}},"4886/26_57":{"rotated":false,"trimmed":true,"sourceSize":{"w":400,"h":400},"spriteSourceSize":{"x":170,"y":146,"w":75,"h":63},"frame":{"x":1,"y":318,"w":75,"h":63}},"4886/26_58":{"rotated":false,"trimmed":true,"sourceSize":{"w":400,"h":400},"spriteSourceSize":{"x":168,"y":147,"w":75,"h":63},"frame":{"x":78,"y":318,"w":75,"h":63}},"4886/26_59":{"rotated":false,"trimmed":true,"sourceSize":{"w":400,"h":400},"spriteSourceSize":{"x":166,"y":148,"w":76,"h":62},"frame":{"x":440,"y":125,"w":76,"h":62}},"4886/26_60":{"rotated":false,"trimmed":true,"sourceSize":{"w":400,"h":400},"spriteSourceSize":{"x":164,"y":149,"w":79,"h":62},"frame":{"x":518,"y":126,"w":79,"h":62}},"4886/26_61":{"rotated":false,"trimmed":true,"sourceSize":{"w":400,"h":400},"spriteSourceSize":{"x":164,"y":149,"w":77,"h":62},"frame":{"x":599,"y":127,"w":77,"h":62}},"4886/26_62":{"rotated":false,"trimmed":true,"sourceSize":{"w":400,"h":400},"spriteSourceSize":{"x":164,"y":148,"w":75,"h":62},"frame":{"x":678,"y":128,"w":75,"h":62}},"4886/26_63":{"rotated":false,"trimmed":true,"sourceSize":{"w":400,"h":400},"spriteSourceSize":{"x":165,"y":147,"w":71,"h":63},"frame":{"x":155,"y":318,"w":71,"h":63}},"4886/26_64":{"rotated":false,"trimmed":true,"sourceSize":{"w":400,"h":400},"spriteSourceSize":{"x":165,"y":147,"w":67,"h":63},"frame":{"x":423,"y":253,"w":67,"h":63}},"4886/26_65":{"rotated":false,"trimmed":true,"sourceSize":{"w":400,"h":400},"spriteSourceSize":{"x":166,"y":146,"w":61,"h":63},"frame":{"x":951,"y":199,"w":61,"h":63}},"4886/26_66":{"rotated":false,"trimmed":true,"sourceSize":{"w":400,"h":400},"spriteSourceSize":{"x":166,"y":145,"w":59,"h":63},"frame":{"x":492,"y":254,"w":59,"h":63}},"4886/26_67":{"rotated":false,"trimmed":true,"sourceSize":{"w":400,"h":400},"spriteSourceSize":{"x":167,"y":143,"w":59,"h":64},"frame":{"x":955,"y":330,"w":59,"h":64}},"4886/26_68":{"rotated":false,"trimmed":true,"sourceSize":{"w":400,"h":400},"spriteSourceSize":{"x":168,"y":143,"w":59,"h":63},"frame":{"x":553,"y":256,"w":59,"h":63}},"4886/26_69":{"rotated":false,"trimmed":true,"sourceSize":{"w":400,"h":400},"spriteSourceSize":{"x":170,"y":143,"w":59,"h":63},"frame":{"x":614,"y":257,"w":59,"h":63}},"4886/26_70":{"rotated":false,"trimmed":true,"sourceSize":{"w":400,"h":400},"spriteSourceSize":{"x":171,"y":144,"w":59,"h":62},"frame":{"x":379,"y":125,"w":59,"h":62}},"4886/26_71":{"rotated":false,"trimmed":true,"sourceSize":{"w":400,"h":400},"spriteSourceSize":{"x":173,"y":143,"w":61,"h":63},"frame":{"x":675,"y":257,"w":61,"h":63}},"4886/26_72":{"rotated":false,"trimmed":true,"sourceSize":{"w":400,"h":400},"spriteSourceSize":{"x":174,"y":143,"w":65,"h":63},"frame":{"x":738,"y":257,"w":65,"h":63}},"4886/26_73":{"rotated":false,"trimmed":true,"sourceSize":{"w":400,"h":400},"spriteSourceSize":{"x":174,"y":143,"w":69,"h":64},"frame":{"x":209,"y":383,"w":69,"h":64}},"4886/26_74":{"rotated":false,"trimmed":true,"sourceSize":{"w":400,"h":400},"spriteSourceSize":{"x":173,"y":145,"w":73,"h":63},"frame":{"x":871,"y":264,"w":73,"h":63}},"4886/26_75":{"rotated":false,"trimmed":true,"sourceSize":{"w":400,"h":400},"spriteSourceSize":{"x":170,"y":146,"w":75,"h":63},"frame":{"x":1,"y":318,"w":75,"h":63}},"4886/26_76":{"rotated":false,"trimmed":true,"sourceSize":{"w":400,"h":400},"spriteSourceSize":{"x":168,"y":147,"w":75,"h":63},"frame":{"x":78,"y":318,"w":75,"h":63}},"4886/26_77":{"rotated":false,"trimmed":true,"sourceSize":{"w":400,"h":400},"spriteSourceSize":{"x":166,"y":148,"w":76,"h":62},"frame":{"x":440,"y":125,"w":76,"h":62}},"4886/26_78":{"rotated":false,"trimmed":true,"sourceSize":{"w":400,"h":400},"spriteSourceSize":{"x":164,"y":149,"w":79,"h":62},"frame":{"x":518,"y":126,"w":79,"h":62}},"4886/26_79":{"rotated":false,"trimmed":true,"sourceSize":{"w":400,"h":400},"spriteSourceSize":{"x":164,"y":149,"w":77,"h":62},"frame":{"x":599,"y":127,"w":77,"h":62}},"4886/26_80":{"rotated":false,"trimmed":true,"sourceSize":{"w":400,"h":400},"spriteSourceSize":{"x":164,"y":148,"w":75,"h":62},"frame":{"x":678,"y":128,"w":75,"h":62}},"4886/26_81":{"rotated":false,"trimmed":true,"sourceSize":{"w":400,"h":400},"spriteSourceSize":{"x":165,"y":147,"w":71,"h":63},"frame":{"x":155,"y":318,"w":71,"h":63}},"4886/26_82":{"rotated":false,"trimmed":true,"sourceSize":{"w":400,"h":400},"spriteSourceSize":{"x":162,"y":147,"w":76,"h":61},"frame":{"x":145,"y":62,"w":76,"h":61}},"4886/26_83":{"rotated":false,"trimmed":true,"sourceSize":{"w":400,"h":400},"spriteSourceSize":{"x":162,"y":147,"w":76,"h":61},"frame":{"x":145,"y":62,"w":76,"h":61}},"4886/26_84":{"rotated":false,"trimmed":true,"sourceSize":{"w":400,"h":400},"spriteSourceSize":{"x":162,"y":147,"w":76,"h":61},"frame":{"x":145,"y":62,"w":76,"h":61}},"4886/26_85":{"rotated":false,"trimmed":true,"sourceSize":{"w":400,"h":400},"spriteSourceSize":{"x":164,"y":154,"w":74,"h":61},"frame":{"x":223,"y":62,"w":74,"h":61}},"4886/26_86":{"rotated":false,"trimmed":true,"sourceSize":{"w":400,"h":400},"spriteSourceSize":{"x":164,"y":154,"w":74,"h":61},"frame":{"x":223,"y":62,"w":74,"h":61}},"4886/26_87":{"rotated":false,"trimmed":true,"sourceSize":{"w":400,"h":400},"spriteSourceSize":{"x":164,"y":154,"w":74,"h":61},"frame":{"x":223,"y":62,"w":74,"h":61}},"4886/26_88":{"rotated":false,"trimmed":true,"sourceSize":{"w":400,"h":400},"spriteSourceSize":{"x":164,"y":154,"w":74,"h":61},"frame":{"x":223,"y":62,"w":74,"h":61}},"4886/26_89":{"rotated":false,"trimmed":true,"sourceSize":{"w":400,"h":400},"spriteSourceSize":{"x":162,"y":147,"w":76,"h":61},"frame":{"x":145,"y":62,"w":76,"h":61}},"4886/26_90":{"rotated":false,"trimmed":true,"sourceSize":{"w":400,"h":400},"spriteSourceSize":{"x":162,"y":147,"w":76,"h":61},"frame":{"x":145,"y":62,"w":76,"h":61}},"4886/26_91":{"rotated":false,"trimmed":true,"sourceSize":{"w":400,"h":400},"spriteSourceSize":{"x":162,"y":147,"w":76,"h":61},"frame":{"x":145,"y":62,"w":76,"h":61}},"4886/26_92":{"rotated":false,"trimmed":true,"sourceSize":{"w":400,"h":400},"spriteSourceSize":{"x":164,"y":154,"w":74,"h":61},"frame":{"x":223,"y":62,"w":74,"h":61}},"4886/26_93":{"rotated":false,"trimmed":true,"sourceSize":{"w":400,"h":400},"spriteSourceSize":{"x":164,"y":154,"w":74,"h":61},"frame":{"x":223,"y":62,"w":74,"h":61}},"4886/26_94":{"rotated":false,"trimmed":true,"sourceSize":{"w":400,"h":400},"spriteSourceSize":{"x":164,"y":154,"w":74,"h":61},"frame":{"x":223,"y":62,"w":74,"h":61}},"4886/26_95":{"rotated":false,"trimmed":true,"sourceSize":{"w":400,"h":400},"spriteSourceSize":{"x":164,"y":154,"w":74,"h":61},"frame":{"x":223,"y":62,"w":74,"h":61}},"4886/26_96":{"rotated":false,"trimmed":true,"sourceSize":{"w":400,"h":400},"spriteSourceSize":{"x":162,"y":147,"w":76,"h":61},"frame":{"x":145,"y":62,"w":76,"h":61}},"4886/26_97":{"rotated":false,"trimmed":true,"sourceSize":{"w":400,"h":400},"spriteSourceSize":{"x":162,"y":147,"w":76,"h":61},"frame":{"x":145,"y":62,"w":76,"h":61}},"4886/26_98":{"rotated":false,"trimmed":true,"sourceSize":{"w":400,"h":400},"spriteSourceSize":{"x":162,"y":147,"w":76,"h":61},"frame":{"x":145,"y":62,"w":76,"h":61}},"4886/26_99":{"rotated":false,"trimmed":true,"sourceSize":{"w":400,"h":400},"spriteSourceSize":{"x":162,"y":147,"w":76,"h":61},"frame":{"x":803,"y":1,"w":76,"h":61}},"4886/26_100":{"rotated":false,"trimmed":true,"sourceSize":{"w":400,"h":400},"spriteSourceSize":{"x":161,"y":146,"w":76,"h":62},"frame":{"x":223,"y":125,"w":76,"h":62}},"4886/26_101":{"rotated":false,"trimmed":true,"sourceSize":{"w":400,"h":400},"spriteSourceSize":{"x":160,"y":145,"w":90,"h":63},"frame":{"x":239,"y":253,"w":90,"h":63}},"4886/26_102":{"rotated":false,"trimmed":true,"sourceSize":{"w":400,"h":400},"spriteSourceSize":{"x":159,"y":135,"w":93,"h":73},"frame":{"x":818,"y":1093,"w":93,"h":73}},"4886/26_103":{"rotated":false,"trimmed":true,"sourceSize":{"w":400,"h":400},"spriteSourceSize":{"x":159,"y":142,"w":82,"h":66},"frame":{"x":600,"y":521,"w":82,"h":66}},"4886/26_104":{"rotated":false,"trimmed":true,"sourceSize":{"w":400,"h":400},"spriteSourceSize":{"x":159,"y":142,"w":80,"h":66},"frame":{"x":815,"y":530,"w":80,"h":66}},"4886/26_105":{"rotated":false,"trimmed":true,"sourceSize":{"w":400,"h":400},"spriteSourceSize":{"x":159,"y":142,"w":80,"h":66},"frame":{"x":815,"y":530,"w":80,"h":66}},"4886/26_106":{"rotated":false,"trimmed":true,"sourceSize":{"w":400,"h":400},"spriteSourceSize":{"x":159,"y":142,"w":81,"h":66},"frame":{"x":897,"y":531,"w":81,"h":66}},"4886/26_107":{"rotated":false,"trimmed":true,"sourceSize":{"w":400,"h":400},"spriteSourceSize":{"x":159,"y":142,"w":82,"h":66},"frame":{"x":1,"y":583,"w":82,"h":66}},"4886/26_108":{"rotated":false,"trimmed":true,"sourceSize":{"w":400,"h":400},"spriteSourceSize":{"x":159,"y":142,"w":83,"h":66},"frame":{"x":85,"y":583,"w":83,"h":66}},"4886/26_109":{"rotated":false,"trimmed":true,"sourceSize":{"w":400,"h":400},"spriteSourceSize":{"x":159,"y":142,"w":83,"h":66},"frame":{"x":85,"y":583,"w":83,"h":66}},"4886/26_110":{"rotated":false,"trimmed":true,"sourceSize":{"w":400,"h":400},"spriteSourceSize":{"x":162,"y":147,"w":76,"h":61},"frame":{"x":145,"y":62,"w":76,"h":61}},"4886/26_111":{"rotated":false,"trimmed":true,"sourceSize":{"w":400,"h":400},"spriteSourceSize":{"x":162,"y":147,"w":76,"h":61},"frame":{"x":145,"y":62,"w":76,"h":61}},"4886/26_112":{"rotated":false,"trimmed":true,"sourceSize":{"w":400,"h":400},"spriteSourceSize":{"x":162,"y":147,"w":76,"h":61},"frame":{"x":145,"y":62,"w":76,"h":61}},"4886/26_113":{"rotated":false,"trimmed":true,"sourceSize":{"w":400,"h":400},"spriteSourceSize":{"x":164,"y":154,"w":74,"h":61},"frame":{"x":223,"y":62,"w":74,"h":61}},"4886/26_114":{"rotated":false,"trimmed":true,"sourceSize":{"w":400,"h":400},"spriteSourceSize":{"x":164,"y":154,"w":74,"h":61},"frame":{"x":223,"y":62,"w":74,"h":61}},"4886/26_115":{"rotated":false,"trimmed":true,"sourceSize":{"w":400,"h":400},"spriteSourceSize":{"x":164,"y":154,"w":74,"h":61},"frame":{"x":223,"y":62,"w":74,"h":61}},"4886/26_116":{"rotated":false,"trimmed":true,"sourceSize":{"w":400,"h":400},"spriteSourceSize":{"x":164,"y":154,"w":74,"h":61},"frame":{"x":223,"y":62,"w":74,"h":61}},"4886/26_117":{"rotated":false,"trimmed":true,"sourceSize":{"w":400,"h":400},"spriteSourceSize":{"x":162,"y":147,"w":76,"h":61},"frame":{"x":145,"y":62,"w":76,"h":61}},"4886/26_118":{"rotated":false,"trimmed":true,"sourceSize":{"w":400,"h":400},"spriteSourceSize":{"x":162,"y":147,"w":76,"h":61},"frame":{"x":145,"y":62,"w":76,"h":61}},"4886/26_119":{"rotated":false,"trimmed":true,"sourceSize":{"w":400,"h":400},"spriteSourceSize":{"x":162,"y":147,"w":76,"h":61},"frame":{"x":145,"y":62,"w":76,"h":61}},"4886/26_120":{"rotated":false,"trimmed":true,"sourceSize":{"w":400,"h":400},"spriteSourceSize":{"x":164,"y":154,"w":74,"h":61},"frame":{"x":223,"y":62,"w":74,"h":61}},"4886/26_121":{"rotated":false,"trimmed":true,"sourceSize":{"w":400,"h":400},"spriteSourceSize":{"x":164,"y":154,"w":74,"h":61},"frame":{"x":223,"y":62,"w":74,"h":61}},"4886/26_122":{"rotated":false,"trimmed":true,"sourceSize":{"w":400,"h":400},"spriteSourceSize":{"x":164,"y":154,"w":74,"h":61},"frame":{"x":223,"y":62,"w":74,"h":61}},"4886/26_123":{"rotated":false,"trimmed":true,"sourceSize":{"w":400,"h":400},"spriteSourceSize":{"x":164,"y":154,"w":74,"h":61},"frame":{"x":223,"y":62,"w":74,"h":61}},"4886/26_124":{"rotated":false,"trimmed":true,"sourceSize":{"w":400,"h":400},"spriteSourceSize":{"x":162,"y":147,"w":76,"h":61},"frame":{"x":145,"y":62,"w":76,"h":61}},"4886/26_125":{"rotated":false,"trimmed":true,"sourceSize":{"w":400,"h":400},"spriteSourceSize":{"x":162,"y":147,"w":76,"h":61},"frame":{"x":145,"y":62,"w":76,"h":61}},"4886/26_126":{"rotated":false,"trimmed":true,"sourceSize":{"w":400,"h":400},"spriteSourceSize":{"x":162,"y":147,"w":76,"h":61},"frame":{"x":145,"y":62,"w":76,"h":61}},"4886/26_127":{"rotated":false,"trimmed":true,"sourceSize":{"w":400,"h":400},"spriteSourceSize":{"x":162,"y":147,"w":76,"h":61},"frame":{"x":145,"y":62,"w":76,"h":61}},"4886/26_128":{"rotated":false,"trimmed":true,"sourceSize":{"w":400,"h":400},"spriteSourceSize":{"x":164,"y":146,"w":76,"h":62},"frame":{"x":301,"y":125,"w":76,"h":62}},"4886/26_129":{"rotated":false,"trimmed":true,"sourceSize":{"w":400,"h":400},"spriteSourceSize":{"x":151,"y":145,"w":90,"h":63},"frame":{"x":331,"y":253,"w":90,"h":63}},"4886/26_130":{"rotated":false,"trimmed":true,"sourceSize":{"w":400,"h":400},"spriteSourceSize":{"x":148,"y":135,"w":94,"h":73},"frame":{"x":913,"y":1093,"w":94,"h":73}},"4886/26_131":{"rotated":false,"trimmed":true,"sourceSize":{"w":400,"h":400},"spriteSourceSize":{"x":159,"y":142,"w":82,"h":66},"frame":{"x":170,"y":583,"w":82,"h":66}},"4886/26_132":{"rotated":false,"trimmed":true,"sourceSize":{"w":400,"h":400},"spriteSourceSize":{"x":161,"y":141,"w":80,"h":67},"frame":{"x":335,"y":654,"w":80,"h":67}},"4886/26_133":{"rotated":false,"trimmed":true,"sourceSize":{"w":400,"h":400},"spriteSourceSize":{"x":161,"y":141,"w":80,"h":67},"frame":{"x":335,"y":654,"w":80,"h":67}},"4886/26_134":{"rotated":false,"trimmed":true,"sourceSize":{"w":400,"h":400},"spriteSourceSize":{"x":160,"y":142,"w":81,"h":66},"frame":{"x":254,"y":585,"w":81,"h":66}},"4886/26_135":{"rotated":false,"trimmed":true,"sourceSize":{"w":400,"h":400},"spriteSourceSize":{"x":159,"y":142,"w":82,"h":66},"frame":{"x":337,"y":586,"w":82,"h":66}},"4886/26_136":{"rotated":false,"trimmed":true,"sourceSize":{"w":400,"h":400},"spriteSourceSize":{"x":158,"y":142,"w":83,"h":66},"frame":{"x":421,"y":588,"w":83,"h":66}},"4886/26_137":{"rotated":false,"trimmed":true,"sourceSize":{"w":400,"h":400},"spriteSourceSize":{"x":158,"y":142,"w":83,"h":66},"frame":{"x":421,"y":588,"w":83,"h":66}},"4886/26_138":{"rotated":false,"trimmed":true,"sourceSize":{"w":400,"h":400},"spriteSourceSize":{"x":162,"y":147,"w":76,"h":61},"frame":{"x":145,"y":62,"w":76,"h":61}},"4886/26_139":{"rotated":false,"trimmed":true,"sourceSize":{"w":400,"h":400},"spriteSourceSize":{"x":162,"y":147,"w":76,"h":61},"frame":{"x":145,"y":62,"w":76,"h":61}},"4886/26_140":{"rotated":false,"trimmed":true,"sourceSize":{"w":400,"h":400},"spriteSourceSize":{"x":162,"y":147,"w":76,"h":61},"frame":{"x":145,"y":62,"w":76,"h":61}},"4886/26_141":{"rotated":false,"trimmed":true,"sourceSize":{"w":400,"h":400},"spriteSourceSize":{"x":164,"y":154,"w":74,"h":61},"frame":{"x":223,"y":62,"w":74,"h":61}},"4886/26_142":{"rotated":false,"trimmed":true,"sourceSize":{"w":400,"h":400},"spriteSourceSize":{"x":164,"y":154,"w":74,"h":61},"frame":{"x":223,"y":62,"w":74,"h":61}},"4886/26_143":{"rotated":false,"trimmed":true,"sourceSize":{"w":400,"h":400},"spriteSourceSize":{"x":164,"y":154,"w":74,"h":61},"frame":{"x":223,"y":62,"w":74,"h":61}},"4886/26_144":{"rotated":false,"trimmed":true,"sourceSize":{"w":400,"h":400},"spriteSourceSize":{"x":164,"y":154,"w":74,"h":61},"frame":{"x":223,"y":62,"w":74,"h":61}},"4886/26_145":{"rotated":false,"trimmed":true,"sourceSize":{"w":400,"h":400},"spriteSourceSize":{"x":162,"y":147,"w":76,"h":61},"frame":{"x":145,"y":62,"w":76,"h":61}},"4886/26_146":{"rotated":false,"trimmed":true,"sourceSize":{"w":400,"h":400},"spriteSourceSize":{"x":162,"y":147,"w":76,"h":61},"frame":{"x":145,"y":62,"w":76,"h":61}},"4886/26_147":{"rotated":false,"trimmed":true,"sourceSize":{"w":400,"h":400},"spriteSourceSize":{"x":162,"y":147,"w":76,"h":61},"frame":{"x":145,"y":62,"w":76,"h":61}},"4886/26_148":{"rotated":false,"trimmed":true,"sourceSize":{"w":400,"h":400},"spriteSourceSize":{"x":164,"y":154,"w":74,"h":61},"frame":{"x":223,"y":62,"w":74,"h":61}},"4886/26_149":{"rotated":false,"trimmed":true,"sourceSize":{"w":400,"h":400},"spriteSourceSize":{"x":164,"y":154,"w":74,"h":61},"frame":{"x":223,"y":62,"w":74,"h":61}},"4886/26_150":{"rotated":false,"trimmed":true,"sourceSize":{"w":400,"h":400},"spriteSourceSize":{"x":164,"y":154,"w":74,"h":61},"frame":{"x":223,"y":62,"w":74,"h":61}},"4886/26_151":{"rotated":false,"trimmed":true,"sourceSize":{"w":400,"h":400},"spriteSourceSize":{"x":164,"y":154,"w":74,"h":61},"frame":{"x":223,"y":62,"w":74,"h":61}},"4886/26_152":{"rotated":false,"trimmed":true,"sourceSize":{"w":400,"h":400},"spriteSourceSize":{"x":162,"y":147,"w":76,"h":61},"frame":{"x":145,"y":62,"w":76,"h":61}},"4886/26_153":{"rotated":false,"trimmed":true,"sourceSize":{"w":400,"h":400},"spriteSourceSize":{"x":162,"y":147,"w":76,"h":61},"frame":{"x":145,"y":62,"w":76,"h":61}},"4886/26_154":{"rotated":false,"trimmed":true,"sourceSize":{"w":400,"h":400},"spriteSourceSize":{"x":162,"y":147,"w":76,"h":61},"frame":{"x":145,"y":62,"w":76,"h":61}},"4886/26_155":{"rotated":false,"trimmed":true,"sourceSize":{"w":400,"h":400},"spriteSourceSize":{"x":165,"y":146,"w":63,"h":64},"frame":{"x":826,"y":329,"w":63,"h":64}},"4886/26_156":{"rotated":false,"trimmed":true,"sourceSize":{"w":400,"h":400},"spriteSourceSize":{"x":171,"y":151,"w":64,"h":67},"frame":{"x":187,"y":651,"w":64,"h":67}},"4886/26_157":{"rotated":false,"trimmed":true,"sourceSize":{"w":400,"h":400},"spriteSourceSize":{"x":174,"y":159,"w":68,"h":69},"frame":{"x":114,"y":859,"w":68,"h":69}},"4886/26_158":{"rotated":false,"trimmed":true,"sourceSize":{"w":400,"h":400},"spriteSourceSize":{"x":178,"y":163,"w":69,"h":72},"frame":{"x":258,"y":1077,"w":69,"h":72}},"4886/26_159":{"rotated":false,"trimmed":true,"sourceSize":{"w":400,"h":400},"spriteSourceSize":{"x":178,"y":163,"w":69,"h":72},"frame":{"x":258,"y":1077,"w":69,"h":72}},"4886/26_160":{"rotated":false,"trimmed":true,"sourceSize":{"w":400,"h":400},"spriteSourceSize":{"x":178,"y":163,"w":69,"h":72},"frame":{"x":258,"y":1077,"w":69,"h":72}},"4886/26_161":{"rotated":false,"trimmed":true,"sourceSize":{"w":400,"h":400},"spriteSourceSize":{"x":178,"y":163,"w":69,"h":72},"frame":{"x":258,"y":1077,"w":69,"h":72}},"4886/26_162":{"rotated":false,"trimmed":true,"sourceSize":{"w":400,"h":400},"spriteSourceSize":{"x":174,"y":159,"w":68,"h":69},"frame":{"x":114,"y":859,"w":68,"h":69}},"4886/26_163":{"rotated":false,"trimmed":true,"sourceSize":{"w":400,"h":400},"spriteSourceSize":{"x":171,"y":151,"w":64,"h":67},"frame":{"x":187,"y":651,"w":64,"h":67}},"4886/26_164":{"rotated":false,"trimmed":true,"sourceSize":{"w":400,"h":400},"spriteSourceSize":{"x":165,"y":146,"w":63,"h":64},"frame":{"x":826,"y":329,"w":63,"h":64}},"4886/26_165":{"rotated":false,"trimmed":true,"sourceSize":{"w":400,"h":400},"spriteSourceSize":{"x":165,"y":146,"w":63,"h":64},"frame":{"x":826,"y":329,"w":63,"h":64}},"4886/26_166":{"rotated":false,"trimmed":true,"sourceSize":{"w":400,"h":400},"spriteSourceSize":{"x":162,"y":147,"w":76,"h":61},"frame":{"x":145,"y":62,"w":76,"h":61}},"4886/26_167":{"rotated":false,"trimmed":true,"sourceSize":{"w":400,"h":400},"spriteSourceSize":{"x":162,"y":147,"w":76,"h":61},"frame":{"x":145,"y":62,"w":76,"h":61}},"4886/26_168":{"rotated":false,"trimmed":true,"sourceSize":{"w":400,"h":400},"spriteSourceSize":{"x":162,"y":147,"w":76,"h":61},"frame":{"x":145,"y":62,"w":76,"h":61}},"4886/26_169":{"rotated":false,"trimmed":true,"sourceSize":{"w":400,"h":400},"spriteSourceSize":{"x":164,"y":154,"w":74,"h":61},"frame":{"x":223,"y":62,"w":74,"h":61}},"4886/26_170":{"rotated":false,"trimmed":true,"sourceSize":{"w":400,"h":400},"spriteSourceSize":{"x":164,"y":154,"w":74,"h":61},"frame":{"x":223,"y":62,"w":74,"h":61}},"4886/26_171":{"rotated":false,"trimmed":true,"sourceSize":{"w":400,"h":400},"spriteSourceSize":{"x":164,"y":154,"w":74,"h":61},"frame":{"x":223,"y":62,"w":74,"h":61}},"4886/26_172":{"rotated":false,"trimmed":true,"sourceSize":{"w":400,"h":400},"spriteSourceSize":{"x":164,"y":154,"w":74,"h":61},"frame":{"x":223,"y":62,"w":74,"h":61}},"4886/26_173":{"rotated":false,"trimmed":true,"sourceSize":{"w":400,"h":400},"spriteSourceSize":{"x":162,"y":147,"w":76,"h":61},"frame":{"x":145,"y":62,"w":76,"h":61}},"4886/26_174":{"rotated":false,"trimmed":true,"sourceSize":{"w":400,"h":400},"spriteSourceSize":{"x":162,"y":147,"w":76,"h":61},"frame":{"x":145,"y":62,"w":76,"h":61}},"4886/26_175":{"rotated":false,"trimmed":true,"sourceSize":{"w":400,"h":400},"spriteSourceSize":{"x":162,"y":147,"w":76,"h":61},"frame":{"x":145,"y":62,"w":76,"h":61}},"4886/26_176":{"rotated":false,"trimmed":true,"sourceSize":{"w":400,"h":400},"spriteSourceSize":{"x":164,"y":154,"w":74,"h":61},"frame":{"x":223,"y":62,"w":74,"h":61}},"4886/26_177":{"rotated":false,"trimmed":true,"sourceSize":{"w":400,"h":400},"spriteSourceSize":{"x":164,"y":154,"w":74,"h":61},"frame":{"x":223,"y":62,"w":74,"h":61}},"4886/26_178":{"rotated":false,"trimmed":true,"sourceSize":{"w":400,"h":400},"spriteSourceSize":{"x":164,"y":154,"w":74,"h":61},"frame":{"x":223,"y":62,"w":74,"h":61}},"4886/26_179":{"rotated":false,"trimmed":true,"sourceSize":{"w":400,"h":400},"spriteSourceSize":{"x":164,"y":154,"w":74,"h":61},"frame":{"x":223,"y":62,"w":74,"h":61}},"4886/26_180":{"rotated":false,"trimmed":true,"sourceSize":{"w":400,"h":400},"spriteSourceSize":{"x":162,"y":147,"w":76,"h":61},"frame":{"x":145,"y":62,"w":76,"h":61}},"4886/26_181":{"rotated":false,"trimmed":true,"sourceSize":{"w":400,"h":400},"spriteSourceSize":{"x":162,"y":147,"w":76,"h":61},"frame":{"x":145,"y":62,"w":76,"h":61}},"4886/26_182":{"rotated":false,"trimmed":true,"sourceSize":{"w":400,"h":400},"spriteSourceSize":{"x":162,"y":147,"w":76,"h":61},"frame":{"x":145,"y":62,"w":76,"h":61}},"4886/26_183":{"rotated":false,"trimmed":true,"sourceSize":{"w":400,"h":400},"spriteSourceSize":{"x":176,"y":146,"w":62,"h":64},"frame":{"x":891,"y":330,"w":62,"h":64}},"4886/26_184":{"rotated":false,"trimmed":true,"sourceSize":{"w":400,"h":400},"spriteSourceSize":{"x":169,"y":151,"w":63,"h":67},"frame":{"x":417,"y":656,"w":63,"h":67}},"4886/26_185":{"rotated":false,"trimmed":true,"sourceSize":{"w":400,"h":400},"spriteSourceSize":{"x":162,"y":159,"w":67,"h":70},"frame":{"x":477,"y":937,"w":67,"h":70}},"4886/26_186":{"rotated":false,"trimmed":true,"sourceSize":{"w":400,"h":400},"spriteSourceSize":{"x":157,"y":163,"w":69,"h":73},"frame":{"x":652,"y":1093,"w":69,"h":73}},"4886/26_187":{"rotated":false,"trimmed":true,"sourceSize":{"w":400,"h":400},"spriteSourceSize":{"x":157,"y":163,"w":69,"h":73},"frame":{"x":652,"y":1093,"w":69,"h":73}},"4886/26_188":{"rotated":false,"trimmed":true,"sourceSize":{"w":400,"h":400},"spriteSourceSize":{"x":157,"y":163,"w":69,"h":73},"frame":{"x":652,"y":1093,"w":69,"h":73}},"4886/26_189":{"rotated":false,"trimmed":true,"sourceSize":{"w":400,"h":400},"spriteSourceSize":{"x":157,"y":163,"w":69,"h":73},"frame":{"x":652,"y":1093,"w":69,"h":73}},"4886/26_190":{"rotated":false,"trimmed":true,"sourceSize":{"w":400,"h":400},"spriteSourceSize":{"x":162,"y":159,"w":67,"h":70},"frame":{"x":477,"y":937,"w":67,"h":70}},"4886/26_191":{"rotated":false,"trimmed":true,"sourceSize":{"w":400,"h":400},"spriteSourceSize":{"x":169,"y":151,"w":63,"h":67},"frame":{"x":417,"y":656,"w":63,"h":67}},"4886/26_192":{"rotated":false,"trimmed":true,"sourceSize":{"w":400,"h":400},"spriteSourceSize":{"x":176,"y":146,"w":62,"h":64},"frame":{"x":891,"y":330,"w":62,"h":64}},"4886/26_193":{"rotated":false,"trimmed":true,"sourceSize":{"w":400,"h":400},"spriteSourceSize":{"x":176,"y":146,"w":62,"h":64},"frame":{"x":891,"y":330,"w":62,"h":64}},"4886/27_1":{"rotated":false,"trimmed":true,"sourceSize":{"w":400,"h":400},"spriteSourceSize":{"x":174,"y":145,"w":63,"h":64},"frame":{"x":280,"y":383,"w":63,"h":64}},"4886/27_2":{"rotated":false,"trimmed":true,"sourceSize":{"w":400,"h":400},"spriteSourceSize":{"x":168,"y":150,"w":63,"h":67},"frame":{"x":613,"y":657,"w":63,"h":67}},"4886/27_3":{"rotated":false,"trimmed":true,"sourceSize":{"w":400,"h":400},"spriteSourceSize":{"x":161,"y":158,"w":67,"h":69},"frame":{"x":184,"y":861,"w":67,"h":69}},"4886/27_4":{"rotated":false,"trimmed":true,"sourceSize":{"w":400,"h":400},"spriteSourceSize":{"x":155,"y":162,"w":69,"h":72},"frame":{"x":329,"y":1080,"w":69,"h":72}},"4886/27_5":{"rotated":false,"trimmed":true,"sourceSize":{"w":400,"h":400},"spriteSourceSize":{"x":153,"y":161,"w":71,"h":73},"frame":{"x":1,"y":1148,"w":71,"h":73}},"4886/27_6":{"rotated":false,"trimmed":true,"sourceSize":{"w":400,"h":400},"spriteSourceSize":{"x":160,"y":160,"w":64,"h":65},"frame":{"x":405,"y":451,"w":64,"h":65}},"4886/27_7":{"rotated":false,"trimmed":true,"sourceSize":{"w":400,"h":400},"spriteSourceSize":{"x":160,"y":160,"w":64,"h":62},"frame":{"x":1,"y":189,"w":64,"h":62}},"4886/27_8":{"rotated":false,"trimmed":true,"sourceSize":{"w":400,"h":400},"spriteSourceSize":{"x":160,"y":160,"w":64,"h":59},"frame":{"x":199,"y":1,"w":64,"h":59}},"4886/27_9":{"rotated":false,"trimmed":true,"sourceSize":{"w":400,"h":400},"spriteSourceSize":{"x":160,"y":160,"w":64,"h":59},"frame":{"x":265,"y":1,"w":64,"h":59}},"4886/27_10":{"rotated":false,"trimmed":true,"sourceSize":{"w":400,"h":400},"spriteSourceSize":{"x":160,"y":160,"w":64,"h":59},"frame":{"x":1,"y":1,"w":64,"h":59}},"4886/27_11":{"rotated":false,"trimmed":true,"sourceSize":{"w":400,"h":400},"spriteSourceSize":{"x":160,"y":160,"w":64,"h":59},"frame":{"x":67,"y":1,"w":64,"h":59}},"4886/27_12":{"rotated":false,"trimmed":true,"sourceSize":{"w":400,"h":400},"spriteSourceSize":{"x":160,"y":160,"w":64,"h":59},"frame":{"x":133,"y":1,"w":64,"h":59}},"4886/27_13":{"rotated":false,"trimmed":true,"sourceSize":{"w":400,"h":400},"spriteSourceSize":{"x":162,"y":159,"w":65,"h":62},"frame":{"x":755,"y":128,"w":65,"h":62}},"4886/27_14":{"rotated":false,"trimmed":true,"sourceSize":{"w":400,"h":400},"spriteSourceSize":{"x":164,"y":156,"w":65,"h":67},"frame":{"x":482,"y":657,"w":65,"h":67}},"4886/27_15":{"rotated":false,"trimmed":true,"sourceSize":{"w":400,"h":400},"spriteSourceSize":{"x":171,"y":150,"w":62,"h":67},"frame":{"x":549,"y":657,"w":62,"h":67}},"4886/27_16":{"rotated":false,"trimmed":true,"sourceSize":{"w":400,"h":400},"spriteSourceSize":{"x":175,"y":145,"w":65,"h":62},"frame":{"x":822,"y":128,"w":65,"h":62}},"4886/27_17":{"rotated":false,"trimmed":true,"sourceSize":{"w":400,"h":400},"spriteSourceSize":{"x":174,"y":144,"w":76,"h":62},"frame":{"x":889,"y":135,"w":76,"h":62}},"4886/27_18":{"rotated":false,"trimmed":true,"sourceSize":{"w":400,"h":400},"spriteSourceSize":{"x":172,"y":128,"w":86,"h":78},"frame":{"x":313,"y":1155,"w":86,"h":78}},"4886/27_19":{"rotated":false,"trimmed":true,"sourceSize":{"w":400,"h":400},"spriteSourceSize":{"x":171,"y":134,"w":87,"h":72},"frame":{"x":400,"y":1081,"w":87,"h":72}},"4886/27_20":{"rotated":false,"trimmed":true,"sourceSize":{"w":400,"h":400},"spriteSourceSize":{"x":171,"y":139,"w":85,"h":68},"frame":{"x":853,"y":736,"w":85,"h":68}},"4886/27_21":{"rotated":false,"trimmed":true,"sourceSize":{"w":400,"h":400},"spriteSourceSize":{"x":173,"y":144,"w":61,"h":64},"frame":{"x":345,"y":384,"w":61,"h":64}},"4886/27_22":{"rotated":false,"trimmed":true,"sourceSize":{"w":400,"h":400},"spriteSourceSize":{"x":169,"y":146,"w":64,"h":64},"frame":{"x":408,"y":385,"w":64,"h":64}},"4886/27_23":{"rotated":false,"trimmed":true,"sourceSize":{"w":400,"h":400},"spriteSourceSize":{"x":173,"y":146,"w":60,"h":65},"frame":{"x":343,"y":450,"w":60,"h":65}},"4886/27_24":{"rotated":false,"trimmed":true,"sourceSize":{"w":400,"h":400},"spriteSourceSize":{"x":173,"y":148,"w":59,"h":70},"frame":{"x":660,"y":947,"w":59,"h":70}},"4886/27_25":{"rotated":false,"trimmed":true,"sourceSize":{"w":400,"h":400},"spriteSourceSize":{"x":174,"y":146,"w":59,"h":70},"frame":{"x":721,"y":948,"w":59,"h":70}},"4886/27_26":{"rotated":false,"trimmed":true,"sourceSize":{"w":400,"h":400},"spriteSourceSize":{"x":174,"y":146,"w":63,"h":64},"frame":{"x":474,"y":387,"w":63,"h":64}},"4886/27_27":{"rotated":false,"trimmed":true,"sourceSize":{"w":400,"h":400},"spriteSourceSize":{"x":174,"y":146,"w":63,"h":64},"frame":{"x":539,"y":387,"w":63,"h":64}},"4886/27_28":{"rotated":false,"trimmed":true,"sourceSize":{"w":400,"h":400},"spriteSourceSize":{"x":174,"y":145,"w":63,"h":64},"frame":{"x":604,"y":388,"w":63,"h":64}},"4886/28_1":{"rotated":false,"trimmed":true,"sourceSize":{"w":400,"h":400},"spriteSourceSize":{"x":172,"y":152,"w":64,"h":66},"frame":{"x":133,"y":515,"w":64,"h":66}},"4886/28_2":{"rotated":false,"trimmed":true,"sourceSize":{"w":400,"h":400},"spriteSourceSize":{"x":163,"y":147,"w":69,"h":68},"frame":{"x":128,"y":789,"w":69,"h":68}},"4886/28_3":{"rotated":false,"trimmed":true,"sourceSize":{"w":400,"h":400},"spriteSourceSize":{"x":155,"y":143,"w":74,"h":70},"frame":{"x":919,"y":948,"w":74,"h":70}},"4886/28_4":{"rotated":false,"trimmed":true,"sourceSize":{"w":400,"h":400},"spriteSourceSize":{"x":154,"y":141,"w":72,"h":69},"frame":{"x":436,"y":866,"w":72,"h":69}},"4886/28_5":{"rotated":false,"trimmed":true,"sourceSize":{"w":400,"h":400},"spriteSourceSize":{"x":156,"y":141,"w":71,"h":69},"frame":{"x":510,"y":866,"w":71,"h":69}},"4886/28_6":{"rotated":false,"trimmed":true,"sourceSize":{"w":400,"h":400},"spriteSourceSize":{"x":164,"y":141,"w":64,"h":68},"frame":{"x":260,"y":792,"w":64,"h":68}},"4886/28_7":{"rotated":false,"trimmed":true,"sourceSize":{"w":400,"h":400},"spriteSourceSize":{"x":165,"y":140,"w":63,"h":69},"frame":{"x":583,"y":868,"w":63,"h":69}},"4886/28_8":{"rotated":false,"trimmed":true,"sourceSize":{"w":400,"h":400},"spriteSourceSize":{"x":167,"y":140,"w":61,"h":69},"frame":{"x":648,"y":875,"w":61,"h":69}},"4886/28_9":{"rotated":false,"trimmed":true,"sourceSize":{"w":400,"h":400},"spriteSourceSize":{"x":167,"y":140,"w":61,"h":69},"frame":{"x":711,"y":876,"w":61,"h":69}},"4886/28_10":{"rotated":false,"trimmed":true,"sourceSize":{"w":400,"h":400},"spriteSourceSize":{"x":167,"y":140,"w":61,"h":69},"frame":{"x":310,"y":862,"w":61,"h":69}},"4886/28_11":{"rotated":false,"trimmed":true,"sourceSize":{"w":400,"h":400},"spriteSourceSize":{"x":167,"y":140,"w":61,"h":69},"frame":{"x":373,"y":865,"w":61,"h":69}},"4886/28_12":{"rotated":false,"trimmed":true,"sourceSize":{"w":400,"h":400},"spriteSourceSize":{"x":167,"y":140,"w":61,"h":70},"frame":{"x":782,"y":948,"w":61,"h":70}},"4886/28_13":{"rotated":false,"trimmed":true,"sourceSize":{"w":400,"h":400},"spriteSourceSize":{"x":164,"y":141,"w":64,"h":71},"frame":{"x":951,"y":1020,"w":64,"h":71}},"4886/28_14":{"rotated":false,"trimmed":true,"sourceSize":{"w":400,"h":400},"spriteSourceSize":{"x":160,"y":143,"w":69,"h":71},"frame":{"x":1,"y":1073,"w":69,"h":71}},"4886/28_15":{"rotated":false,"trimmed":true,"sourceSize":{"w":400,"h":400},"spriteSourceSize":{"x":159,"y":147,"w":72,"h":70},"frame":{"x":845,"y":948,"w":72,"h":70}},"4886/28_16":{"rotated":false,"trimmed":true,"sourceSize":{"w":400,"h":400},"spriteSourceSize":{"x":160,"y":152,"w":74,"h":68},"frame":{"x":940,"y":736,"w":74,"h":68}},"4886/28_17":{"rotated":false,"trimmed":true,"sourceSize":{"w":400,"h":400},"spriteSourceSize":{"x":168,"y":152,"w":67,"h":68},"frame":{"x":59,"y":789,"w":67,"h":68}},"4886/28_18":{"rotated":false,"trimmed":true,"sourceSize":{"w":400,"h":400},"spriteSourceSize":{"x":180,"y":151,"w":55,"h":69},"frame":{"x":253,"y":862,"w":55,"h":69}},"4886/28_19":{"rotated":false,"trimmed":true,"sourceSize":{"w":400,"h":400},"spriteSourceSize":{"x":179,"y":152,"w":56,"h":68},"frame":{"x":1,"y":788,"w":56,"h":68}},"4886/28_20":{"rotated":false,"trimmed":true,"sourceSize":{"w":400,"h":400},"spriteSourceSize":{"x":176,"y":152,"w":59,"h":68},"frame":{"x":199,"y":791,"w":59,"h":68}},"4886/28_21":{"rotated":false,"trimmed":true,"sourceSize":{"w":400,"h":400},"spriteSourceSize":{"x":162,"y":141,"w":73,"h":77},"frame":{"x":74,"y":1149,"w":73,"h":77}},"4886/28_22":{"rotated":false,"trimmed":true,"sourceSize":{"w":400,"h":400},"spriteSourceSize":{"x":167,"y":136,"w":71,"h":81},"frame":{"x":473,"y":1158,"w":71,"h":81}},"4886/28_23":{"rotated":false,"trimmed":true,"sourceSize":{"w":400,"h":400},"spriteSourceSize":{"x":161,"y":149,"w":75,"h":67},"frame":{"x":744,"y":666,"w":75,"h":67}},"4886/28_24":{"rotated":false,"trimmed":true,"sourceSize":{"w":400,"h":400},"spriteSourceSize":{"x":159,"y":148,"w":76,"h":67},"frame":{"x":821,"y":667,"w":76,"h":67}},"4886/28_25":{"rotated":false,"trimmed":true,"sourceSize":{"w":400,"h":400},"spriteSourceSize":{"x":163,"y":150,"w":72,"h":66},"frame":{"x":506,"y":589,"w":72,"h":66}},"4886/28_26":{"rotated":false,"trimmed":true,"sourceSize":{"w":400,"h":400},"spriteSourceSize":{"x":172,"y":151,"w":64,"h":66},"frame":{"x":645,"y":589,"w":64,"h":66}},"4886/28_27":{"rotated":false,"trimmed":true,"sourceSize":{"w":400,"h":400},"spriteSourceSize":{"x":172,"y":151,"w":64,"h":66},"frame":{"x":711,"y":597,"w":64,"h":66}},"4886/28_28":{"rotated":false,"trimmed":true,"sourceSize":{"w":400,"h":400},"spriteSourceSize":{"x":172,"y":151,"w":64,"h":67},"frame":{"x":678,"y":665,"w":64,"h":67}},"4886/29_1":{"rotated":false,"trimmed":true,"sourceSize":{"w":400,"h":400},"spriteSourceSize":{"x":165,"y":151,"w":64,"h":66},"frame":{"x":777,"y":598,"w":64,"h":66}},"4886/29_2":{"rotated":false,"trimmed":true,"sourceSize":{"w":400,"h":400},"spriteSourceSize":{"x":169,"y":146,"w":69,"h":68},"frame":{"x":472,"y":796,"w":69,"h":68}},"4886/29_3":{"rotated":false,"trimmed":true,"sourceSize":{"w":400,"h":400},"spriteSourceSize":{"x":172,"y":143,"w":74,"h":70},"frame":{"x":267,"y":1005,"w":74,"h":70}},"4886/29_4":{"rotated":false,"trimmed":true,"sourceSize":{"w":400,"h":400},"spriteSourceSize":{"x":175,"y":141,"w":71,"h":69},"frame":{"x":837,"y":877,"w":71,"h":69}},"4886/29_5":{"rotated":false,"trimmed":true,"sourceSize":{"w":400,"h":400},"spriteSourceSize":{"x":174,"y":140,"w":70,"h":70},"frame":{"x":343,"y":1008,"w":70,"h":70}},"4886/29_6":{"rotated":false,"trimmed":true,"sourceSize":{"w":400,"h":400},"spriteSourceSize":{"x":173,"y":140,"w":64,"h":69},"frame":{"x":910,"y":877,"w":64,"h":69}},"4886/29_7":{"rotated":false,"trimmed":true,"sourceSize":{"w":400,"h":400},"spriteSourceSize":{"x":173,"y":139,"w":63,"h":70},"frame":{"x":415,"y":1009,"w":63,"h":70}},"4886/29_8":{"rotated":false,"trimmed":true,"sourceSize":{"w":400,"h":400},"spriteSourceSize":{"x":173,"y":140,"w":61,"h":69},"frame":{"x":1,"y":930,"w":61,"h":69}},"4886/29_9":{"rotated":false,"trimmed":true,"sourceSize":{"w":400,"h":400},"spriteSourceSize":{"x":173,"y":140,"w":61,"h":69},"frame":{"x":64,"y":930,"w":61,"h":69}},"4886/29_10":{"rotated":false,"trimmed":true,"sourceSize":{"w":400,"h":400},"spriteSourceSize":{"x":173,"y":140,"w":61,"h":69},"frame":{"x":774,"y":877,"w":61,"h":69}},"4886/29_11":{"rotated":false,"trimmed":true,"sourceSize":{"w":400,"h":400},"spriteSourceSize":{"x":173,"y":139,"w":61,"h":70},"frame":{"x":1,"y":1001,"w":61,"h":70}},"4886/29_12":{"rotated":false,"trimmed":true,"sourceSize":{"w":400,"h":400},"spriteSourceSize":{"x":173,"y":139,"w":61,"h":70},"frame":{"x":64,"y":1001,"w":61,"h":70}},"4886/29_13":{"rotated":false,"trimmed":true,"sourceSize":{"w":400,"h":400},"spriteSourceSize":{"x":173,"y":141,"w":64,"h":70},"frame":{"x":127,"y":1003,"w":64,"h":70}},"4886/29_14":{"rotated":false,"trimmed":true,"sourceSize":{"w":400,"h":400},"spriteSourceSize":{"x":172,"y":142,"w":69,"h":71},"frame":{"x":187,"y":1077,"w":69,"h":71}},"4886/29_15":{"rotated":false,"trimmed":true,"sourceSize":{"w":400,"h":400},"spriteSourceSize":{"x":170,"y":147,"w":72,"h":70},"frame":{"x":193,"y":1005,"w":72,"h":70}},"4886/29_16":{"rotated":false,"trimmed":true,"sourceSize":{"w":400,"h":400},"spriteSourceSize":{"x":167,"y":151,"w":74,"h":68},"frame":{"x":326,"y":792,"w":74,"h":68}},"4886/29_17":{"rotated":false,"trimmed":true,"sourceSize":{"w":400,"h":400},"spriteSourceSize":{"x":166,"y":151,"w":68,"h":68},"frame":{"x":402,"y":795,"w":68,"h":68}},"4886/29_18":{"rotated":false,"trimmed":true,"sourceSize":{"w":400,"h":400},"spriteSourceSize":{"x":166,"y":151,"w":55,"h":68},"frame":{"x":960,"y":1,"w":55,"h":68}},"4886/29_19":{"rotated":false,"trimmed":true,"sourceSize":{"w":400,"h":400},"spriteSourceSize":{"x":166,"y":152,"w":56,"h":67},"frame":{"x":959,"y":462,"w":56,"h":67}},"4886/29_20":{"rotated":false,"trimmed":true,"sourceSize":{"w":400,"h":400},"spriteSourceSize":{"x":166,"y":151,"w":60,"h":68},"frame":{"x":543,"y":796,"w":60,"h":68}},"4886/29_21":{"rotated":false,"trimmed":true,"sourceSize":{"w":400,"h":400},"spriteSourceSize":{"x":166,"y":141,"w":73,"h":77},"frame":{"x":149,"y":1150,"w":73,"h":77}},"4886/29_22":{"rotated":false,"trimmed":true,"sourceSize":{"w":400,"h":400},"spriteSourceSize":{"x":164,"y":136,"w":70,"h":80},"frame":{"x":401,"y":1155,"w":70,"h":80}},"4886/29_23":{"rotated":false,"trimmed":true,"sourceSize":{"w":400,"h":400},"spriteSourceSize":{"x":165,"y":149,"w":75,"h":67},"frame":{"x":899,"y":667,"w":75,"h":67}},"4886/29_24":{"rotated":false,"trimmed":true,"sourceSize":{"w":400,"h":400},"spriteSourceSize":{"x":167,"y":148,"w":75,"h":67},"frame":{"x":66,"y":720,"w":75,"h":67}},"4886/29_25":{"rotated":false,"trimmed":true,"sourceSize":{"w":400,"h":400},"spriteSourceSize":{"x":166,"y":149,"w":72,"h":67},"frame":{"x":143,"y":720,"w":72,"h":67}},"4886/29_26":{"rotated":false,"trimmed":true,"sourceSize":{"w":400,"h":400},"spriteSourceSize":{"x":166,"y":150,"w":63,"h":67},"frame":{"x":1,"y":719,"w":63,"h":67}},"4886/29_27":{"rotated":false,"trimmed":true,"sourceSize":{"w":400,"h":400},"spriteSourceSize":{"x":166,"y":151,"w":63,"h":66},"frame":{"x":580,"y":589,"w":63,"h":66}},"4886/29_28":{"rotated":false,"trimmed":true,"sourceSize":{"w":400,"h":400},"spriteSourceSize":{"x":165,"y":151,"w":64,"h":66},"frame":{"x":843,"y":599,"w":64,"h":66}},"4886/30_1":{"rotated":false,"trimmed":true,"sourceSize":{"w":400,"h":400},"spriteSourceSize":{"x":162,"y":145,"w":63,"h":64},"frame":{"x":669,"y":388,"w":63,"h":64}},"4886/30_2":{"rotated":false,"trimmed":true,"sourceSize":{"w":400,"h":400},"spriteSourceSize":{"x":168,"y":149,"w":64,"h":67},"frame":{"x":349,"y":723,"w":64,"h":67}},"4886/30_3":{"rotated":false,"trimmed":true,"sourceSize":{"w":400,"h":400},"spriteSourceSize":{"x":171,"y":157,"w":68,"h":69},"frame":{"x":114,"y":859,"w":68,"h":69}},"4886/30_4":{"rotated":false,"trimmed":true,"sourceSize":{"w":400,"h":400},"spriteSourceSize":{"x":175,"y":161,"w":69,"h":72},"frame":{"x":258,"y":1077,"w":69,"h":72}},"4886/30_5":{"rotated":false,"trimmed":true,"sourceSize":{"w":400,"h":400},"spriteSourceSize":{"x":175,"y":160,"w":71,"h":72},"frame":{"x":579,"y":1091,"w":71,"h":72}},"4886/30_6":{"rotated":false,"trimmed":true,"sourceSize":{"w":400,"h":400},"spriteSourceSize":{"x":175,"y":159,"w":64,"h":65},"frame":{"x":695,"y":454,"w":64,"h":65}},"4886/30_7":{"rotated":false,"trimmed":true,"sourceSize":{"w":400,"h":400},"spriteSourceSize":{"x":175,"y":159,"w":65,"h":62},"frame":{"x":280,"y":189,"w":65,"h":62}},"4886/30_8":{"rotated":false,"trimmed":true,"sourceSize":{"w":400,"h":400},"spriteSourceSize":{"x":175,"y":159,"w":64,"h":59},"frame":{"x":530,"y":1,"w":64,"h":59}},"4886/30_9":{"rotated":false,"trimmed":true,"sourceSize":{"w":400,"h":400},"spriteSourceSize":{"x":175,"y":159,"w":64,"h":59},"frame":{"x":596,"y":1,"w":64,"h":59}},"4886/30_10":{"rotated":false,"trimmed":true,"sourceSize":{"w":400,"h":400},"spriteSourceSize":{"x":175,"y":159,"w":64,"h":59},"frame":{"x":331,"y":1,"w":64,"h":59}},"4886/30_11":{"rotated":false,"trimmed":true,"sourceSize":{"w":400,"h":400},"spriteSourceSize":{"x":175,"y":159,"w":64,"h":59},"frame":{"x":397,"y":1,"w":64,"h":59}},"4886/30_12":{"rotated":false,"trimmed":true,"sourceSize":{"w":400,"h":400},"spriteSourceSize":{"x":175,"y":159,"w":65,"h":59},"frame":{"x":463,"y":1,"w":65,"h":59}},"4886/30_13":{"rotated":false,"trimmed":true,"sourceSize":{"w":400,"h":400},"spriteSourceSize":{"x":173,"y":158,"w":65,"h":62},"frame":{"x":67,"y":189,"w":65,"h":62}},"4886/30_14":{"rotated":false,"trimmed":true,"sourceSize":{"w":400,"h":400},"spriteSourceSize":{"x":170,"y":155,"w":66,"h":67},"frame":{"x":217,"y":722,"w":66,"h":67}},"4886/30_15":{"rotated":false,"trimmed":true,"sourceSize":{"w":400,"h":400},"spriteSourceSize":{"x":167,"y":149,"w":62,"h":67},"frame":{"x":285,"y":723,"w":62,"h":67}},"4886/30_16":{"rotated":false,"trimmed":true,"sourceSize":{"w":400,"h":400},"spriteSourceSize":{"x":159,"y":144,"w":65,"h":62},"frame":{"x":134,"y":189,"w":65,"h":62}},"4886/30_17":{"rotated":false,"trimmed":true,"sourceSize":{"w":400,"h":400},"spriteSourceSize":{"x":149,"y":144,"w":77,"h":62},"frame":{"x":201,"y":189,"w":77,"h":62}},"4886/30_18":{"rotated":false,"trimmed":true,"sourceSize":{"w":400,"h":400},"spriteSourceSize":{"x":141,"y":128,"w":87,"h":77},"frame":{"x":224,"y":1151,"w":87,"h":77}},"4886/30_19":{"rotated":false,"trimmed":true,"sourceSize":{"w":400,"h":400},"spriteSourceSize":{"x":141,"y":133,"w":88,"h":72},"frame":{"x":489,"y":1084,"w":88,"h":72}},"4886/30_20":{"rotated":false,"trimmed":true,"sourceSize":{"w":400,"h":400},"spriteSourceSize":{"x":143,"y":139,"w":86,"h":67},"frame":{"x":415,"y":726,"w":86,"h":67}},"4886/30_21":{"rotated":false,"trimmed":true,"sourceSize":{"w":400,"h":400},"spriteSourceSize":{"x":166,"y":143,"w":60,"h":64},"frame":{"x":734,"y":388,"w":60,"h":64}},"4886/30_22":{"rotated":false,"trimmed":true,"sourceSize":{"w":400,"h":400},"spriteSourceSize":{"x":166,"y":145,"w":65,"h":64},"frame":{"x":796,"y":395,"w":65,"h":64}},"4886/30_23":{"rotated":false,"trimmed":true,"sourceSize":{"w":400,"h":400},"spriteSourceSize":{"x":167,"y":146,"w":59,"h":64},"frame":{"x":863,"y":396,"w":59,"h":64}},"4886/30_24":{"rotated":false,"trimmed":true,"sourceSize":{"w":400,"h":400},"spriteSourceSize":{"x":167,"y":147,"w":60,"h":70},"frame":{"x":480,"y":1009,"w":60,"h":70}},"4886/30_25":{"rotated":false,"trimmed":true,"sourceSize":{"w":400,"h":400},"spriteSourceSize":{"x":167,"y":146,"w":59,"h":69},"frame":{"x":184,"y":932,"w":59,"h":69}},"4886/30_26":{"rotated":false,"trimmed":true,"sourceSize":{"w":400,"h":400},"spriteSourceSize":{"x":162,"y":145,"w":64,"h":64},"frame":{"x":924,"y":396,"w":64,"h":64}},"4886/30_27":{"rotated":false,"trimmed":true,"sourceSize":{"w":400,"h":400},"spriteSourceSize":{"x":162,"y":145,"w":63,"h":64},"frame":{"x":1,"y":449,"w":63,"h":64}},"4886/30_28":{"rotated":false,"trimmed":true,"sourceSize":{"w":400,"h":400},"spriteSourceSize":{"x":161,"y":145,"w":64,"h":63},"frame":{"x":805,"y":257,"w":64,"h":63}}}}