{"meta":{"app":"https://www.codeandweb.com/texturepacker","version":"3.0","smartupdate":"$TexturePacker:SmartUpdate:a783dd48b5d50530651e84914208d0de:6860075eac22e58b3eb4ecaf580f90de:3fc605e98a5689959365345227b105fc$","image":"asset.webp","format":"RGBA8888","size":{"w":2039,"h":543},"scale":"1"},"frames":{"769/1_1":{"rotated":false,"trimmed":true,"sourceSize":{"w":400,"h":400},"spriteSourceSize":{"x":162,"y":151,"w":76,"h":48},"frame":{"x":1,"y":1,"w":76,"h":48}},"769/2_1":{"rotated":false,"trimmed":true,"sourceSize":{"w":400,"h":400},"spriteSourceSize":{"x":175,"y":141,"w":59,"h":69},"frame":{"x":683,"y":297,"w":59,"h":69}},"769/3_1":{"rotated":false,"trimmed":true,"sourceSize":{"w":400,"h":400},"spriteSourceSize":{"x":183,"y":139,"w":45,"h":83},"frame":{"x":1614,"y":456,"w":45,"h":83}},"769/4_1":{"rotated":false,"trimmed":true,"sourceSize":{"w":400,"h":400},"spriteSourceSize":{"x":174,"y":147,"w":59,"h":70},"frame":{"x":1,"y":359,"w":59,"h":70}},"769/5_1":{"rotated":false,"trimmed":true,"sourceSize":{"w":400,"h":400},"spriteSourceSize":{"x":162,"y":159,"w":76,"h":51},"frame":{"x":1886,"y":1,"w":76,"h":51}},"769/6_1":{"rotated":false,"trimmed":true,"sourceSize":{"w":400,"h":400},"spriteSourceSize":{"x":168,"y":147,"w":59,"h":70},"frame":{"x":62,"y":360,"w":59,"h":70}},"769/7_1":{"rotated":false,"trimmed":true,"sourceSize":{"w":400,"h":400},"spriteSourceSize":{"x":172,"y":139,"w":45,"h":83},"frame":{"x":1661,"y":457,"w":45,"h":83}},"769/8_1":{"rotated":false,"trimmed":true,"sourceSize":{"w":400,"h":400},"spriteSourceSize":{"x":164,"y":141,"w":59,"h":69},"frame":{"x":1232,"y":304,"w":59,"h":69}},"769/9_1":{"rotated":false,"trimmed":true,"sourceSize":{"w":400,"h":400},"spriteSourceSize":{"x":161,"y":143,"w":73,"h":59},"frame":{"x":1584,"y":111,"w":73,"h":59}},"769/9_2":{"rotated":false,"trimmed":true,"sourceSize":{"w":400,"h":400},"spriteSourceSize":{"x":161,"y":146,"w":74,"h":55},"frame":{"x":1842,"y":54,"w":74,"h":55}},"769/9_3":{"rotated":false,"trimmed":true,"sourceSize":{"w":400,"h":400},"spriteSourceSize":{"x":161,"y":149,"w":74,"h":51},"frame":{"x":1964,"y":1,"w":74,"h":51}},"769/9_4":{"rotated":false,"trimmed":true,"sourceSize":{"w":400,"h":400},"spriteSourceSize":{"x":162,"y":149,"w":75,"h":51},"frame":{"x":1,"y":51,"w":75,"h":51}},"769/9_5":{"rotated":false,"trimmed":true,"sourceSize":{"w":400,"h":400},"spriteSourceSize":{"x":165,"y":143,"w":73,"h":59},"frame":{"x":1659,"y":111,"w":73,"h":59}},"769/9_6":{"rotated":false,"trimmed":true,"sourceSize":{"w":400,"h":400},"spriteSourceSize":{"x":164,"y":146,"w":74,"h":55},"frame":{"x":1918,"y":54,"w":74,"h":55}},"769/9_7":{"rotated":false,"trimmed":true,"sourceSize":{"w":400,"h":400},"spriteSourceSize":{"x":163,"y":149,"w":75,"h":51},"frame":{"x":78,"y":51,"w":75,"h":51}},"769/9_8":{"rotated":false,"trimmed":true,"sourceSize":{"w":400,"h":400},"spriteSourceSize":{"x":161,"y":149,"w":76,"h":51},"frame":{"x":155,"y":51,"w":76,"h":51}},"769/10_1":{"rotated":false,"trimmed":true,"sourceSize":{"w":400,"h":400},"spriteSourceSize":{"x":167,"y":153,"w":72,"h":49},"frame":{"x":391,"y":1,"w":72,"h":49}},"769/10_2":{"rotated":false,"trimmed":true,"sourceSize":{"w":400,"h":400},"spriteSourceSize":{"x":169,"y":149,"w":68,"h":55},"frame":{"x":1248,"y":54,"w":68,"h":55}},"769/10_3":{"rotated":false,"trimmed":true,"sourceSize":{"w":400,"h":400},"spriteSourceSize":{"x":171,"y":145,"w":65,"h":62},"frame":{"x":748,"y":167,"w":65,"h":62}},"769/10_4":{"rotated":false,"trimmed":true,"sourceSize":{"w":400,"h":400},"spriteSourceSize":{"x":178,"y":139,"w":51,"h":76},"frame":{"x":1611,"y":378,"w":51,"h":76}},"769/10_5":{"rotated":false,"trimmed":true,"sourceSize":{"w":400,"h":400},"spriteSourceSize":{"x":179,"y":138,"w":45,"h":81},"frame":{"x":703,"y":442,"w":45,"h":81}},"769/10_6":{"rotated":false,"trimmed":true,"sourceSize":{"w":400,"h":400},"spriteSourceSize":{"x":179,"y":139,"w":48,"h":79},"frame":{"x":190,"y":434,"w":48,"h":79}},"769/10_7":{"rotated":false,"trimmed":true,"sourceSize":{"w":400,"h":400},"spriteSourceSize":{"x":179,"y":141,"w":51,"h":76},"frame":{"x":1664,"y":379,"w":51,"h":76}},"769/10_8":{"rotated":false,"trimmed":true,"sourceSize":{"w":400,"h":400},"spriteSourceSize":{"x":171,"y":148,"w":66,"h":61},"frame":{"x":70,"y":162,"w":66,"h":61}},"769/11_1":{"rotated":false,"trimmed":true,"sourceSize":{"w":400,"h":400},"spriteSourceSize":{"x":181,"y":142,"w":49,"h":78},"frame":{"x":1977,"y":391,"w":49,"h":78}},"769/11_2":{"rotated":false,"trimmed":true,"sourceSize":{"w":400,"h":400},"spriteSourceSize":{"x":183,"y":140,"w":46,"h":80},"frame":{"x":604,"y":442,"w":46,"h":80}},"769/11_3":{"rotated":false,"trimmed":true,"sourceSize":{"w":400,"h":400},"spriteSourceSize":{"x":183,"y":139,"w":45,"h":81},"frame":{"x":750,"y":442,"w":45,"h":81}},"769/11_4":{"rotated":false,"trimmed":true,"sourceSize":{"w":400,"h":400},"spriteSourceSize":{"x":183,"y":139,"w":45,"h":82},"frame":{"x":941,"y":448,"w":45,"h":82}},"769/11_5":{"rotated":false,"trimmed":true,"sourceSize":{"w":400,"h":400},"spriteSourceSize":{"x":180,"y":142,"w":50,"h":79},"frame":{"x":295,"y":436,"w":50,"h":79}},"769/11_6":{"rotated":false,"trimmed":true,"sourceSize":{"w":400,"h":400},"spriteSourceSize":{"x":182,"y":141,"w":47,"h":82},"frame":{"x":1136,"y":450,"w":47,"h":82}},"769/11_7":{"rotated":false,"trimmed":true,"sourceSize":{"w":400,"h":400},"spriteSourceSize":{"x":182,"y":140,"w":46,"h":84},"frame":{"x":1708,"y":457,"w":46,"h":84}},"769/11_8":{"rotated":false,"trimmed":true,"sourceSize":{"w":400,"h":400},"spriteSourceSize":{"x":183,"y":141,"w":46,"h":82},"frame":{"x":1185,"y":452,"w":46,"h":82}},"769/12_1":{"rotated":false,"trimmed":true,"sourceSize":{"w":400,"h":400},"spriteSourceSize":{"x":183,"y":141,"w":45,"h":82},"frame":{"x":1233,"y":452,"w":45,"h":82}},"769/12_2":{"rotated":false,"trimmed":true,"sourceSize":{"w":400,"h":400},"spriteSourceSize":{"x":183,"y":142,"w":47,"h":79},"frame":{"x":347,"y":436,"w":47,"h":79}},"769/12_3":{"rotated":false,"trimmed":true,"sourceSize":{"w":400,"h":400},"spriteSourceSize":{"x":180,"y":144,"w":51,"h":75},"frame":{"x":1220,"y":375,"w":51,"h":75}},"769/12_4":{"rotated":false,"trimmed":true,"sourceSize":{"w":400,"h":400},"spriteSourceSize":{"x":173,"y":151,"w":65,"h":61},"frame":{"x":138,"y":162,"w":65,"h":61}},"769/12_5":{"rotated":false,"trimmed":true,"sourceSize":{"w":400,"h":400},"spriteSourceSize":{"x":169,"y":155,"w":72,"h":52},"frame":{"x":233,"y":51,"w":72,"h":52}},"769/12_6":{"rotated":false,"trimmed":true,"sourceSize":{"w":400,"h":400},"spriteSourceSize":{"x":170,"y":153,"w":69,"h":58},"frame":{"x":656,"y":106,"w":69,"h":58}},"769/12_7":{"rotated":false,"trimmed":true,"sourceSize":{"w":400,"h":400},"spriteSourceSize":{"x":172,"y":150,"w":65,"h":65},"frame":{"x":950,"y":233,"w":65,"h":65}},"769/12_8":{"rotated":false,"trimmed":true,"sourceSize":{"w":400,"h":400},"spriteSourceSize":{"x":180,"y":144,"w":50,"h":77},"frame":{"x":1823,"y":379,"w":50,"h":77}},"769/13_1":{"rotated":false,"trimmed":true,"sourceSize":{"w":400,"h":400},"spriteSourceSize":{"x":162,"y":152,"w":74,"h":60},"frame":{"x":1734,"y":111,"w":74,"h":60}},"769/13_2":{"rotated":false,"trimmed":true,"sourceSize":{"w":400,"h":400},"spriteSourceSize":{"x":162,"y":156,"w":75,"h":56},"frame":{"x":1,"y":104,"w":75,"h":56}},"769/13_3":{"rotated":false,"trimmed":true,"sourceSize":{"w":400,"h":400},"spriteSourceSize":{"x":162,"y":159,"w":76,"h":51},"frame":{"x":1229,"y":1,"w":76,"h":51}},"769/13_4":{"rotated":false,"trimmed":true,"sourceSize":{"w":400,"h":400},"spriteSourceSize":{"x":162,"y":157,"w":76,"h":55},"frame":{"x":1318,"y":54,"w":76,"h":55}},"769/13_5":{"rotated":false,"trimmed":true,"sourceSize":{"w":400,"h":400},"spriteSourceSize":{"x":164,"y":152,"w":73,"h":61},"frame":{"x":205,"y":163,"w":73,"h":61}},"769/13_6":{"rotated":false,"trimmed":true,"sourceSize":{"w":400,"h":400},"spriteSourceSize":{"x":163,"y":156,"w":74,"h":56},"frame":{"x":78,"y":104,"w":74,"h":56}},"769/13_7":{"rotated":false,"trimmed":true,"sourceSize":{"w":400,"h":400},"spriteSourceSize":{"x":162,"y":159,"w":75,"h":51},"frame":{"x":1307,"y":1,"w":75,"h":51}},"769/13_8":{"rotated":false,"trimmed":true,"sourceSize":{"w":400,"h":400},"spriteSourceSize":{"x":161,"y":157,"w":76,"h":54},"frame":{"x":970,"y":53,"w":76,"h":54}},"769/14_1":{"rotated":false,"trimmed":true,"sourceSize":{"w":400,"h":400},"spriteSourceSize":{"x":173,"y":142,"w":45,"h":82},"frame":{"x":1280,"y":452,"w":45,"h":82}},"769/14_2":{"rotated":false,"trimmed":true,"sourceSize":{"w":400,"h":400},"spriteSourceSize":{"x":172,"y":143,"w":46,"h":79},"frame":{"x":396,"y":436,"w":46,"h":79}},"769/14_3":{"rotated":false,"trimmed":true,"sourceSize":{"w":400,"h":400},"spriteSourceSize":{"x":170,"y":145,"w":51,"h":75},"frame":{"x":1362,"y":376,"w":51,"h":75}},"769/14_4":{"rotated":false,"trimmed":true,"sourceSize":{"w":400,"h":400},"spriteSourceSize":{"x":163,"y":152,"w":66,"h":61},"frame":{"x":280,"y":163,"w":66,"h":61}},"769/14_5":{"rotated":false,"trimmed":true,"sourceSize":{"w":400,"h":400},"spriteSourceSize":{"x":160,"y":156,"w":73,"h":52},"frame":{"x":307,"y":51,"w":73,"h":52}},"769/14_6":{"rotated":false,"trimmed":true,"sourceSize":{"w":400,"h":400},"spriteSourceSize":{"x":162,"y":154,"w":69,"h":58},"frame":{"x":727,"y":107,"w":69,"h":58}},"769/14_7":{"rotated":false,"trimmed":true,"sourceSize":{"w":400,"h":400},"spriteSourceSize":{"x":164,"y":151,"w":65,"h":65},"frame":{"x":1017,"y":235,"w":65,"h":65}},"769/14_8":{"rotated":false,"trimmed":true,"sourceSize":{"w":400,"h":400},"spriteSourceSize":{"x":171,"y":145,"w":50,"h":77},"frame":{"x":1875,"y":381,"w":50,"h":77}},"769/15_1":{"rotated":false,"trimmed":true,"sourceSize":{"w":400,"h":400},"spriteSourceSize":{"x":170,"y":143,"w":48,"h":77},"frame":{"x":1927,"y":391,"w":48,"h":77}},"769/15_2":{"rotated":false,"trimmed":true,"sourceSize":{"w":400,"h":400},"spriteSourceSize":{"x":170,"y":140,"w":47,"h":81},"frame":{"x":797,"y":445,"w":47,"h":81}},"769/15_3":{"rotated":false,"trimmed":true,"sourceSize":{"w":400,"h":400},"spriteSourceSize":{"x":171,"y":139,"w":46,"h":81},"frame":{"x":846,"y":446,"w":46,"h":81}},"769/15_4":{"rotated":false,"trimmed":true,"sourceSize":{"w":400,"h":400},"spriteSourceSize":{"x":171,"y":140,"w":46,"h":82},"frame":{"x":1327,"y":453,"w":46,"h":82}},"769/15_5":{"rotated":false,"trimmed":true,"sourceSize":{"w":400,"h":400},"spriteSourceSize":{"x":170,"y":142,"w":49,"h":80},"frame":{"x":652,"y":442,"w":49,"h":80}},"769/15_6":{"rotated":false,"trimmed":true,"sourceSize":{"w":400,"h":400},"spriteSourceSize":{"x":171,"y":141,"w":47,"h":82},"frame":{"x":1375,"y":454,"w":47,"h":82}},"769/15_7":{"rotated":false,"trimmed":true,"sourceSize":{"w":400,"h":400},"spriteSourceSize":{"x":172,"y":141,"w":45,"h":84},"frame":{"x":1756,"y":457,"w":45,"h":84}},"769/15_8":{"rotated":false,"trimmed":true,"sourceSize":{"w":400,"h":400},"spriteSourceSize":{"x":170,"y":141,"w":47,"h":83},"frame":{"x":1424,"y":454,"w":47,"h":83}},"769/16_1":{"rotated":false,"trimmed":true,"sourceSize":{"w":400,"h":400},"spriteSourceSize":{"x":160,"y":153,"w":72,"h":49},"frame":{"x":465,"y":1,"w":72,"h":49}},"769/16_2":{"rotated":false,"trimmed":true,"sourceSize":{"w":400,"h":400},"spriteSourceSize":{"x":162,"y":149,"w":68,"h":55},"frame":{"x":1396,"y":54,"w":68,"h":55}},"769/16_3":{"rotated":false,"trimmed":true,"sourceSize":{"w":400,"h":400},"spriteSourceSize":{"x":163,"y":145,"w":65,"h":62},"frame":{"x":815,"y":167,"w":65,"h":62}},"769/16_4":{"rotated":false,"trimmed":true,"sourceSize":{"w":400,"h":400},"spriteSourceSize":{"x":170,"y":139,"w":51,"h":76},"frame":{"x":1717,"y":379,"w":51,"h":76}},"769/16_5":{"rotated":false,"trimmed":true,"sourceSize":{"w":400,"h":400},"spriteSourceSize":{"x":175,"y":138,"w":45,"h":81},"frame":{"x":894,"y":446,"w":45,"h":81}},"769/16_6":{"rotated":false,"trimmed":true,"sourceSize":{"w":400,"h":400},"spriteSourceSize":{"x":172,"y":139,"w":48,"h":79},"frame":{"x":444,"y":436,"w":48,"h":79}},"769/16_7":{"rotated":false,"trimmed":true,"sourceSize":{"w":400,"h":400},"spriteSourceSize":{"x":169,"y":141,"w":51,"h":76},"frame":{"x":1770,"y":379,"w":51,"h":76}},"769/16_8":{"rotated":false,"trimmed":true,"sourceSize":{"w":400,"h":400},"spriteSourceSize":{"x":162,"y":148,"w":66,"h":61},"frame":{"x":348,"y":165,"w":66,"h":61}},"769/17_1":{"rotated":false,"trimmed":true,"sourceSize":{"w":400,"h":400},"spriteSourceSize":{"x":163,"y":159,"w":76,"h":49},"frame":{"x":539,"y":1,"w":76,"h":49}},"769/18_1":{"rotated":false,"trimmed":true,"sourceSize":{"w":400,"h":400},"spriteSourceSize":{"x":172,"y":149,"w":58,"h":69},"frame":{"x":502,"y":294,"w":58,"h":69}},"769/19_1":{"rotated":false,"trimmed":true,"sourceSize":{"w":400,"h":400},"spriteSourceSize":{"x":179,"y":144,"w":45,"h":84},"frame":{"x":1803,"y":458,"w":45,"h":84}},"769/20_1":{"rotated":false,"trimmed":true,"sourceSize":{"w":400,"h":400},"spriteSourceSize":{"x":171,"y":150,"w":59,"h":70},"frame":{"x":1293,"y":304,"w":59,"h":70}},"769/21_1":{"rotated":false,"trimmed":true,"sourceSize":{"w":400,"h":400},"spriteSourceSize":{"x":163,"y":160,"w":75,"h":51},"frame":{"x":1384,"y":1,"w":75,"h":51}},"769/22_1":{"rotated":false,"trimmed":true,"sourceSize":{"w":400,"h":400},"spriteSourceSize":{"x":170,"y":150,"w":58,"h":70},"frame":{"x":1354,"y":304,"w":58,"h":70}},"769/23_1":{"rotated":false,"trimmed":true,"sourceSize":{"w":400,"h":400},"spriteSourceSize":{"x":177,"y":144,"w":45,"h":83},"frame":{"x":1473,"y":455,"w":45,"h":83}},"769/24_1":{"rotated":false,"trimmed":true,"sourceSize":{"w":400,"h":400},"spriteSourceSize":{"x":168,"y":148,"w":59,"h":70},"frame":{"x":1414,"y":304,"w":59,"h":70}},"769/25_1":{"rotated":false,"trimmed":true,"sourceSize":{"w":400,"h":400},"spriteSourceSize":{"x":162,"y":151,"w":76,"h":48},"frame":{"x":79,"y":1,"w":76,"h":48}},"769/25_2":{"rotated":false,"trimmed":true,"sourceSize":{"w":400,"h":400},"spriteSourceSize":{"x":162,"y":150,"w":75,"h":49},"frame":{"x":617,"y":1,"w":75,"h":49}},"769/25_3":{"rotated":false,"trimmed":true,"sourceSize":{"w":400,"h":400},"spriteSourceSize":{"x":162,"y":148,"w":93,"h":51},"frame":{"x":1461,"y":1,"w":93,"h":51}},"769/25_4":{"rotated":false,"trimmed":true,"sourceSize":{"w":400,"h":400},"spriteSourceSize":{"x":159,"y":129,"w":96,"h":70},"frame":{"x":1536,"y":306,"w":96,"h":70}},"769/25_5":{"rotated":false,"trimmed":true,"sourceSize":{"w":400,"h":400},"spriteSourceSize":{"x":160,"y":136,"w":79,"h":63},"frame":{"x":1565,"y":172,"w":79,"h":63}},"769/25_6":{"rotated":false,"trimmed":true,"sourceSize":{"w":400,"h":400},"spriteSourceSize":{"x":160,"y":136,"w":73,"h":63},"frame":{"x":1646,"y":172,"w":73,"h":63}},"769/25_7":{"rotated":false,"trimmed":true,"sourceSize":{"w":400,"h":400},"spriteSourceSize":{"x":160,"y":136,"w":73,"h":63},"frame":{"x":1646,"y":172,"w":73,"h":63}},"769/25_8":{"rotated":false,"trimmed":true,"sourceSize":{"w":400,"h":400},"spriteSourceSize":{"x":160,"y":136,"w":75,"h":63},"frame":{"x":1721,"y":173,"w":75,"h":63}},"769/25_9":{"rotated":false,"trimmed":true,"sourceSize":{"w":400,"h":400},"spriteSourceSize":{"x":160,"y":136,"w":79,"h":63},"frame":{"x":1798,"y":173,"w":79,"h":63}},"769/25_10":{"rotated":false,"trimmed":true,"sourceSize":{"w":400,"h":400},"spriteSourceSize":{"x":160,"y":137,"w":84,"h":62},"frame":{"x":882,"y":169,"w":84,"h":62}},"769/25_11":{"rotated":false,"trimmed":true,"sourceSize":{"w":400,"h":400},"spriteSourceSize":{"x":160,"y":137,"w":84,"h":62},"frame":{"x":882,"y":169,"w":84,"h":62}},"769/25_12":{"rotated":false,"trimmed":true,"sourceSize":{"w":400,"h":400},"spriteSourceSize":{"x":160,"y":136,"w":79,"h":63},"frame":{"x":1565,"y":172,"w":79,"h":63}},"769/26_1":{"rotated":false,"trimmed":true,"sourceSize":{"w":400,"h":400},"spriteSourceSize":{"x":162,"y":151,"w":76,"h":48},"frame":{"x":157,"y":1,"w":76,"h":48}},"769/26_2":{"rotated":false,"trimmed":true,"sourceSize":{"w":400,"h":400},"spriteSourceSize":{"x":162,"y":151,"w":76,"h":48},"frame":{"x":157,"y":1,"w":76,"h":48}},"769/26_3":{"rotated":false,"trimmed":true,"sourceSize":{"w":400,"h":400},"spriteSourceSize":{"x":162,"y":151,"w":76,"h":48},"frame":{"x":157,"y":1,"w":76,"h":48}},"769/26_4":{"rotated":false,"trimmed":true,"sourceSize":{"w":400,"h":400},"spriteSourceSize":{"x":162,"y":151,"w":76,"h":48},"frame":{"x":157,"y":1,"w":76,"h":48}},"769/26_5":{"rotated":false,"trimmed":true,"sourceSize":{"w":400,"h":400},"spriteSourceSize":{"x":157,"y":150,"w":73,"h":59},"frame":{"x":1246,"y":111,"w":73,"h":59}},"769/26_6":{"rotated":false,"trimmed":true,"sourceSize":{"w":400,"h":400},"spriteSourceSize":{"x":157,"y":150,"w":73,"h":59},"frame":{"x":1246,"y":111,"w":73,"h":59}},"769/26_7":{"rotated":false,"trimmed":true,"sourceSize":{"w":400,"h":400},"spriteSourceSize":{"x":157,"y":150,"w":73,"h":59},"frame":{"x":1246,"y":111,"w":73,"h":59}},"769/26_8":{"rotated":false,"trimmed":true,"sourceSize":{"w":400,"h":400},"spriteSourceSize":{"x":157,"y":150,"w":73,"h":59},"frame":{"x":1246,"y":111,"w":73,"h":59}},"769/26_9":{"rotated":false,"trimmed":true,"sourceSize":{"w":400,"h":400},"spriteSourceSize":{"x":162,"y":151,"w":76,"h":48},"frame":{"x":157,"y":1,"w":76,"h":48}},"769/26_10":{"rotated":false,"trimmed":true,"sourceSize":{"w":400,"h":400},"spriteSourceSize":{"x":162,"y":151,"w":76,"h":48},"frame":{"x":157,"y":1,"w":76,"h":48}},"769/26_11":{"rotated":false,"trimmed":true,"sourceSize":{"w":400,"h":400},"spriteSourceSize":{"x":162,"y":151,"w":76,"h":48},"frame":{"x":157,"y":1,"w":76,"h":48}},"769/26_12":{"rotated":false,"trimmed":true,"sourceSize":{"w":400,"h":400},"spriteSourceSize":{"x":170,"y":150,"w":73,"h":59},"frame":{"x":1113,"y":110,"w":73,"h":59}},"769/26_13":{"rotated":false,"trimmed":true,"sourceSize":{"w":400,"h":400},"spriteSourceSize":{"x":170,"y":150,"w":73,"h":59},"frame":{"x":1113,"y":110,"w":73,"h":59}},"769/26_14":{"rotated":false,"trimmed":true,"sourceSize":{"w":400,"h":400},"spriteSourceSize":{"x":170,"y":150,"w":73,"h":59},"frame":{"x":1113,"y":110,"w":73,"h":59}},"769/26_15":{"rotated":false,"trimmed":true,"sourceSize":{"w":400,"h":400},"spriteSourceSize":{"x":170,"y":150,"w":73,"h":59},"frame":{"x":1113,"y":110,"w":73,"h":59}},"769/26_16":{"rotated":false,"trimmed":true,"sourceSize":{"w":400,"h":400},"spriteSourceSize":{"x":162,"y":151,"w":76,"h":48},"frame":{"x":157,"y":1,"w":76,"h":48}},"769/26_17":{"rotated":false,"trimmed":true,"sourceSize":{"w":400,"h":400},"spriteSourceSize":{"x":162,"y":151,"w":76,"h":48},"frame":{"x":157,"y":1,"w":76,"h":48}},"769/26_18":{"rotated":false,"trimmed":true,"sourceSize":{"w":400,"h":400},"spriteSourceSize":{"x":162,"y":151,"w":76,"h":48},"frame":{"x":157,"y":1,"w":76,"h":48}},"769/26_19":{"rotated":false,"trimmed":true,"sourceSize":{"w":400,"h":400},"spriteSourceSize":{"x":177,"y":142,"w":59,"h":69},"frame":{"x":683,"y":297,"w":59,"h":69}},"769/26_20":{"rotated":false,"trimmed":true,"sourceSize":{"w":400,"h":400},"spriteSourceSize":{"x":184,"y":137,"w":45,"h":83},"frame":{"x":1520,"y":455,"w":45,"h":83}},"769/26_21":{"rotated":false,"trimmed":true,"sourceSize":{"w":400,"h":400},"spriteSourceSize":{"x":175,"y":145,"w":59,"h":71},"frame":{"x":123,"y":361,"w":59,"h":71}},"769/26_22":{"rotated":false,"trimmed":true,"sourceSize":{"w":400,"h":400},"spriteSourceSize":{"x":164,"y":156,"w":75,"h":51},"frame":{"x":1746,"y":1,"w":75,"h":51}},"769/26_23":{"rotated":false,"trimmed":true,"sourceSize":{"w":400,"h":400},"spriteSourceSize":{"x":164,"y":156,"w":75,"h":51},"frame":{"x":1746,"y":1,"w":75,"h":51}},"769/26_24":{"rotated":false,"trimmed":true,"sourceSize":{"w":400,"h":400},"spriteSourceSize":{"x":164,"y":156,"w":75,"h":51},"frame":{"x":1746,"y":1,"w":75,"h":51}},"769/26_25":{"rotated":false,"trimmed":true,"sourceSize":{"w":400,"h":400},"spriteSourceSize":{"x":164,"y":148,"w":74,"h":60},"frame":{"x":1810,"y":111,"w":74,"h":60}},"769/26_26":{"rotated":false,"trimmed":true,"sourceSize":{"w":400,"h":400},"spriteSourceSize":{"x":164,"y":148,"w":74,"h":60},"frame":{"x":1810,"y":111,"w":74,"h":60}},"769/26_27":{"rotated":false,"trimmed":true,"sourceSize":{"w":400,"h":400},"spriteSourceSize":{"x":164,"y":148,"w":74,"h":60},"frame":{"x":1810,"y":111,"w":74,"h":60}},"769/26_28":{"rotated":false,"trimmed":true,"sourceSize":{"w":400,"h":400},"spriteSourceSize":{"x":164,"y":148,"w":74,"h":60},"frame":{"x":1810,"y":111,"w":74,"h":60}},"769/26_29":{"rotated":false,"trimmed":true,"sourceSize":{"w":400,"h":400},"spriteSourceSize":{"x":164,"y":156,"w":75,"h":51},"frame":{"x":1746,"y":1,"w":75,"h":51}},"769/26_30":{"rotated":false,"trimmed":true,"sourceSize":{"w":400,"h":400},"spriteSourceSize":{"x":164,"y":156,"w":75,"h":51},"frame":{"x":1746,"y":1,"w":75,"h":51}},"769/26_31":{"rotated":false,"trimmed":true,"sourceSize":{"w":400,"h":400},"spriteSourceSize":{"x":164,"y":156,"w":75,"h":51},"frame":{"x":1746,"y":1,"w":75,"h":51}},"769/26_32":{"rotated":false,"trimmed":true,"sourceSize":{"w":400,"h":400},"spriteSourceSize":{"x":164,"y":148,"w":73,"h":60},"frame":{"x":1886,"y":111,"w":73,"h":60}},"769/26_33":{"rotated":false,"trimmed":true,"sourceSize":{"w":400,"h":400},"spriteSourceSize":{"x":164,"y":148,"w":73,"h":60},"frame":{"x":1886,"y":111,"w":73,"h":60}},"769/26_34":{"rotated":false,"trimmed":true,"sourceSize":{"w":400,"h":400},"spriteSourceSize":{"x":164,"y":148,"w":73,"h":60},"frame":{"x":1886,"y":111,"w":73,"h":60}},"769/26_35":{"rotated":false,"trimmed":true,"sourceSize":{"w":400,"h":400},"spriteSourceSize":{"x":164,"y":148,"w":73,"h":60},"frame":{"x":1886,"y":111,"w":73,"h":60}},"769/26_36":{"rotated":false,"trimmed":true,"sourceSize":{"w":400,"h":400},"spriteSourceSize":{"x":164,"y":156,"w":75,"h":51},"frame":{"x":1746,"y":1,"w":75,"h":51}},"769/26_37":{"rotated":false,"trimmed":true,"sourceSize":{"w":400,"h":400},"spriteSourceSize":{"x":164,"y":156,"w":75,"h":51},"frame":{"x":1746,"y":1,"w":75,"h":51}},"769/26_38":{"rotated":false,"trimmed":true,"sourceSize":{"w":400,"h":400},"spriteSourceSize":{"x":164,"y":156,"w":75,"h":51},"frame":{"x":1746,"y":1,"w":75,"h":51}},"769/26_39":{"rotated":false,"trimmed":true,"sourceSize":{"w":400,"h":400},"spriteSourceSize":{"x":169,"y":145,"w":58,"h":71},"frame":{"x":184,"y":361,"w":58,"h":71}},"769/26_40":{"rotated":false,"trimmed":true,"sourceSize":{"w":400,"h":400},"spriteSourceSize":{"x":173,"y":137,"w":45,"h":83},"frame":{"x":1567,"y":456,"w":45,"h":83}},"769/26_41":{"rotated":false,"trimmed":true,"sourceSize":{"w":400,"h":400},"spriteSourceSize":{"x":167,"y":142,"w":58,"h":69},"frame":{"x":804,"y":297,"w":58,"h":69}},"769/26_42":{"rotated":false,"trimmed":true,"sourceSize":{"w":400,"h":400},"spriteSourceSize":{"x":162,"y":151,"w":76,"h":48},"frame":{"x":157,"y":1,"w":76,"h":48}},"769/26_43":{"rotated":false,"trimmed":true,"sourceSize":{"w":400,"h":400},"spriteSourceSize":{"x":162,"y":151,"w":76,"h":48},"frame":{"x":157,"y":1,"w":76,"h":48}},"769/26_44":{"rotated":false,"trimmed":true,"sourceSize":{"w":400,"h":400},"spriteSourceSize":{"x":162,"y":151,"w":76,"h":48},"frame":{"x":157,"y":1,"w":76,"h":48}},"769/26_45":{"rotated":false,"trimmed":true,"sourceSize":{"w":400,"h":400},"spriteSourceSize":{"x":162,"y":151,"w":76,"h":48},"frame":{"x":157,"y":1,"w":76,"h":48}},"769/26_46":{"rotated":false,"trimmed":true,"sourceSize":{"w":400,"h":400},"spriteSourceSize":{"x":167,"y":149,"w":63,"h":58},"frame":{"x":798,"y":107,"w":63,"h":58}},"769/26_47":{"rotated":false,"trimmed":true,"sourceSize":{"w":400,"h":400},"spriteSourceSize":{"x":167,"y":148,"w":56,"h":60},"frame":{"x":1188,"y":110,"w":56,"h":60}},"769/26_48":{"rotated":false,"trimmed":true,"sourceSize":{"w":400,"h":400},"spriteSourceSize":{"x":167,"y":146,"w":56,"h":61},"frame":{"x":416,"y":165,"w":56,"h":61}},"769/26_49":{"rotated":false,"trimmed":true,"sourceSize":{"w":400,"h":400},"spriteSourceSize":{"x":168,"y":146,"w":56,"h":57},"frame":{"x":351,"y":106,"w":56,"h":57}},"769/26_50":{"rotated":false,"trimmed":true,"sourceSize":{"w":400,"h":400},"spriteSourceSize":{"x":170,"y":145,"w":55,"h":55},"frame":{"x":1466,"y":54,"w":55,"h":55}},"769/26_51":{"rotated":false,"trimmed":true,"sourceSize":{"w":400,"h":400},"spriteSourceSize":{"x":171,"y":145,"w":56,"h":54},"frame":{"x":1048,"y":53,"w":56,"h":54}},"769/26_52":{"rotated":false,"trimmed":true,"sourceSize":{"w":400,"h":400},"spriteSourceSize":{"x":172,"y":146,"w":57,"h":53},"frame":{"x":774,"y":52,"w":57,"h":53}},"769/26_53":{"rotated":false,"trimmed":true,"sourceSize":{"w":400,"h":400},"spriteSourceSize":{"x":174,"y":145,"w":57,"h":52},"frame":{"x":382,"y":52,"w":57,"h":52}},"769/26_54":{"rotated":false,"trimmed":true,"sourceSize":{"w":400,"h":400},"spriteSourceSize":{"x":176,"y":145,"w":61,"h":51},"frame":{"x":1823,"y":1,"w":61,"h":51}},"769/26_55":{"rotated":false,"trimmed":true,"sourceSize":{"w":400,"h":400},"spriteSourceSize":{"x":176,"y":145,"w":64,"h":53},"frame":{"x":833,"y":52,"w":64,"h":53}},"769/26_56":{"rotated":false,"trimmed":true,"sourceSize":{"w":400,"h":400},"spriteSourceSize":{"x":175,"y":146,"w":69,"h":55},"frame":{"x":1523,"y":54,"w":69,"h":55}},"769/26_57":{"rotated":false,"trimmed":true,"sourceSize":{"w":400,"h":400},"spriteSourceSize":{"x":173,"y":148,"w":69,"h":54},"frame":{"x":1106,"y":53,"w":69,"h":54}},"769/26_58":{"rotated":false,"trimmed":true,"sourceSize":{"w":400,"h":400},"spriteSourceSize":{"x":171,"y":149,"w":69,"h":54},"frame":{"x":1177,"y":54,"w":69,"h":54}},"769/26_59":{"rotated":false,"trimmed":true,"sourceSize":{"w":400,"h":400},"spriteSourceSize":{"x":168,"y":151,"w":72,"h":52},"frame":{"x":441,"y":52,"w":72,"h":52}},"769/26_60":{"rotated":false,"trimmed":true,"sourceSize":{"w":400,"h":400},"spriteSourceSize":{"x":166,"y":154,"w":74,"h":50},"frame":{"x":999,"y":1,"w":74,"h":50}},"769/26_61":{"rotated":false,"trimmed":true,"sourceSize":{"w":400,"h":400},"spriteSourceSize":{"x":167,"y":154,"w":71,"h":49},"frame":{"x":926,"y":1,"w":71,"h":49}},"769/26_62":{"rotated":false,"trimmed":true,"sourceSize":{"w":400,"h":400},"spriteSourceSize":{"x":167,"y":152,"w":69,"h":53},"frame":{"x":899,"y":52,"w":69,"h":53}},"769/26_63":{"rotated":false,"trimmed":true,"sourceSize":{"w":400,"h":400},"spriteSourceSize":{"x":168,"y":150,"w":65,"h":56},"frame":{"x":154,"y":104,"w":65,"h":56}},"769/26_64":{"rotated":false,"trimmed":true,"sourceSize":{"w":400,"h":400},"spriteSourceSize":{"x":167,"y":149,"w":63,"h":58},"frame":{"x":798,"y":107,"w":63,"h":58}},"769/26_65":{"rotated":false,"trimmed":true,"sourceSize":{"w":400,"h":400},"spriteSourceSize":{"x":167,"y":148,"w":56,"h":60},"frame":{"x":1188,"y":110,"w":56,"h":60}},"769/26_66":{"rotated":false,"trimmed":true,"sourceSize":{"w":400,"h":400},"spriteSourceSize":{"x":167,"y":146,"w":56,"h":61},"frame":{"x":416,"y":165,"w":56,"h":61}},"769/26_67":{"rotated":false,"trimmed":true,"sourceSize":{"w":400,"h":400},"spriteSourceSize":{"x":168,"y":146,"w":56,"h":57},"frame":{"x":351,"y":106,"w":56,"h":57}},"769/26_68":{"rotated":false,"trimmed":true,"sourceSize":{"w":400,"h":400},"spriteSourceSize":{"x":170,"y":145,"w":55,"h":55},"frame":{"x":1466,"y":54,"w":55,"h":55}},"769/26_69":{"rotated":false,"trimmed":true,"sourceSize":{"w":400,"h":400},"spriteSourceSize":{"x":171,"y":145,"w":56,"h":54},"frame":{"x":1048,"y":53,"w":56,"h":54}},"769/26_70":{"rotated":false,"trimmed":true,"sourceSize":{"w":400,"h":400},"spriteSourceSize":{"x":172,"y":146,"w":57,"h":53},"frame":{"x":774,"y":52,"w":57,"h":53}},"769/26_71":{"rotated":false,"trimmed":true,"sourceSize":{"w":400,"h":400},"spriteSourceSize":{"x":174,"y":145,"w":57,"h":52},"frame":{"x":382,"y":52,"w":57,"h":52}},"769/26_72":{"rotated":false,"trimmed":true,"sourceSize":{"w":400,"h":400},"spriteSourceSize":{"x":176,"y":145,"w":61,"h":51},"frame":{"x":1823,"y":1,"w":61,"h":51}},"769/26_73":{"rotated":false,"trimmed":true,"sourceSize":{"w":400,"h":400},"spriteSourceSize":{"x":176,"y":145,"w":64,"h":53},"frame":{"x":833,"y":52,"w":64,"h":53}},"769/26_74":{"rotated":false,"trimmed":true,"sourceSize":{"w":400,"h":400},"spriteSourceSize":{"x":175,"y":146,"w":69,"h":55},"frame":{"x":1523,"y":54,"w":69,"h":55}},"769/26_75":{"rotated":false,"trimmed":true,"sourceSize":{"w":400,"h":400},"spriteSourceSize":{"x":173,"y":148,"w":69,"h":54},"frame":{"x":1106,"y":53,"w":69,"h":54}},"769/26_76":{"rotated":false,"trimmed":true,"sourceSize":{"w":400,"h":400},"spriteSourceSize":{"x":171,"y":149,"w":69,"h":54},"frame":{"x":1177,"y":54,"w":69,"h":54}},"769/26_77":{"rotated":false,"trimmed":true,"sourceSize":{"w":400,"h":400},"spriteSourceSize":{"x":168,"y":151,"w":72,"h":52},"frame":{"x":441,"y":52,"w":72,"h":52}},"769/26_78":{"rotated":false,"trimmed":true,"sourceSize":{"w":400,"h":400},"spriteSourceSize":{"x":166,"y":154,"w":74,"h":50},"frame":{"x":999,"y":1,"w":74,"h":50}},"769/26_79":{"rotated":false,"trimmed":true,"sourceSize":{"w":400,"h":400},"spriteSourceSize":{"x":167,"y":154,"w":71,"h":49},"frame":{"x":926,"y":1,"w":71,"h":49}},"769/26_80":{"rotated":false,"trimmed":true,"sourceSize":{"w":400,"h":400},"spriteSourceSize":{"x":167,"y":152,"w":69,"h":53},"frame":{"x":899,"y":52,"w":69,"h":53}},"769/26_81":{"rotated":false,"trimmed":true,"sourceSize":{"w":400,"h":400},"spriteSourceSize":{"x":168,"y":150,"w":65,"h":56},"frame":{"x":154,"y":104,"w":65,"h":56}},"769/26_82":{"rotated":false,"trimmed":true,"sourceSize":{"w":400,"h":400},"spriteSourceSize":{"x":162,"y":151,"w":76,"h":48},"frame":{"x":157,"y":1,"w":76,"h":48}},"769/26_83":{"rotated":false,"trimmed":true,"sourceSize":{"w":400,"h":400},"spriteSourceSize":{"x":162,"y":151,"w":76,"h":48},"frame":{"x":157,"y":1,"w":76,"h":48}},"769/26_84":{"rotated":false,"trimmed":true,"sourceSize":{"w":400,"h":400},"spriteSourceSize":{"x":162,"y":151,"w":76,"h":48},"frame":{"x":157,"y":1,"w":76,"h":48}},"769/26_85":{"rotated":false,"trimmed":true,"sourceSize":{"w":400,"h":400},"spriteSourceSize":{"x":163,"y":160,"w":76,"h":49},"frame":{"x":771,"y":1,"w":76,"h":49}},"769/26_86":{"rotated":false,"trimmed":true,"sourceSize":{"w":400,"h":400},"spriteSourceSize":{"x":163,"y":160,"w":76,"h":49},"frame":{"x":771,"y":1,"w":76,"h":49}},"769/26_87":{"rotated":false,"trimmed":true,"sourceSize":{"w":400,"h":400},"spriteSourceSize":{"x":163,"y":160,"w":76,"h":49},"frame":{"x":771,"y":1,"w":76,"h":49}},"769/26_88":{"rotated":false,"trimmed":true,"sourceSize":{"w":400,"h":400},"spriteSourceSize":{"x":163,"y":160,"w":76,"h":49},"frame":{"x":771,"y":1,"w":76,"h":49}},"769/26_89":{"rotated":false,"trimmed":true,"sourceSize":{"w":400,"h":400},"spriteSourceSize":{"x":162,"y":151,"w":76,"h":48},"frame":{"x":157,"y":1,"w":76,"h":48}},"769/26_90":{"rotated":false,"trimmed":true,"sourceSize":{"w":400,"h":400},"spriteSourceSize":{"x":162,"y":151,"w":76,"h":48},"frame":{"x":157,"y":1,"w":76,"h":48}},"769/26_91":{"rotated":false,"trimmed":true,"sourceSize":{"w":400,"h":400},"spriteSourceSize":{"x":162,"y":151,"w":76,"h":48},"frame":{"x":157,"y":1,"w":76,"h":48}},"769/26_92":{"rotated":false,"trimmed":true,"sourceSize":{"w":400,"h":400},"spriteSourceSize":{"x":163,"y":160,"w":76,"h":49},"frame":{"x":771,"y":1,"w":76,"h":49}},"769/26_93":{"rotated":false,"trimmed":true,"sourceSize":{"w":400,"h":400},"spriteSourceSize":{"x":163,"y":160,"w":76,"h":49},"frame":{"x":771,"y":1,"w":76,"h":49}},"769/26_94":{"rotated":false,"trimmed":true,"sourceSize":{"w":400,"h":400},"spriteSourceSize":{"x":163,"y":160,"w":76,"h":49},"frame":{"x":771,"y":1,"w":76,"h":49}},"769/26_95":{"rotated":false,"trimmed":true,"sourceSize":{"w":400,"h":400},"spriteSourceSize":{"x":163,"y":160,"w":76,"h":49},"frame":{"x":771,"y":1,"w":76,"h":49}},"769/26_96":{"rotated":false,"trimmed":true,"sourceSize":{"w":400,"h":400},"spriteSourceSize":{"x":162,"y":151,"w":76,"h":48},"frame":{"x":157,"y":1,"w":76,"h":48}},"769/26_97":{"rotated":false,"trimmed":true,"sourceSize":{"w":400,"h":400},"spriteSourceSize":{"x":162,"y":151,"w":76,"h":48},"frame":{"x":157,"y":1,"w":76,"h":48}},"769/26_98":{"rotated":false,"trimmed":true,"sourceSize":{"w":400,"h":400},"spriteSourceSize":{"x":162,"y":151,"w":76,"h":48},"frame":{"x":157,"y":1,"w":76,"h":48}},"769/26_99":{"rotated":false,"trimmed":true,"sourceSize":{"w":400,"h":400},"spriteSourceSize":{"x":162,"y":151,"w":76,"h":48},"frame":{"x":313,"y":1,"w":76,"h":48}},"769/26_100":{"rotated":false,"trimmed":true,"sourceSize":{"w":400,"h":400},"spriteSourceSize":{"x":162,"y":150,"w":75,"h":49},"frame":{"x":694,"y":1,"w":75,"h":49}},"769/26_101":{"rotated":false,"trimmed":true,"sourceSize":{"w":400,"h":400},"spriteSourceSize":{"x":162,"y":148,"w":93,"h":51},"frame":{"x":1556,"y":1,"w":93,"h":51}},"769/26_102":{"rotated":false,"trimmed":true,"sourceSize":{"w":400,"h":400},"spriteSourceSize":{"x":159,"y":129,"w":96,"h":70},"frame":{"x":1695,"y":307,"w":96,"h":70}},"769/26_103":{"rotated":false,"trimmed":true,"sourceSize":{"w":400,"h":400},"spriteSourceSize":{"x":160,"y":136,"w":79,"h":63},"frame":{"x":1879,"y":173,"w":79,"h":63}},"769/26_104":{"rotated":false,"trimmed":true,"sourceSize":{"w":400,"h":400},"spriteSourceSize":{"x":160,"y":135,"w":73,"h":64},"frame":{"x":502,"y":228,"w":73,"h":64}},"769/26_105":{"rotated":false,"trimmed":true,"sourceSize":{"w":400,"h":400},"spriteSourceSize":{"x":160,"y":135,"w":73,"h":64},"frame":{"x":502,"y":228,"w":73,"h":64}},"769/26_106":{"rotated":false,"trimmed":true,"sourceSize":{"w":400,"h":400},"spriteSourceSize":{"x":160,"y":135,"w":75,"h":64},"frame":{"x":577,"y":229,"w":75,"h":64}},"769/26_107":{"rotated":false,"trimmed":true,"sourceSize":{"w":400,"h":400},"spriteSourceSize":{"x":160,"y":136,"w":79,"h":63},"frame":{"x":1,"y":225,"w":79,"h":63}},"769/26_108":{"rotated":false,"trimmed":true,"sourceSize":{"w":400,"h":400},"spriteSourceSize":{"x":160,"y":137,"w":84,"h":62},"frame":{"x":968,"y":169,"w":84,"h":62}},"769/26_109":{"rotated":false,"trimmed":true,"sourceSize":{"w":400,"h":400},"spriteSourceSize":{"x":160,"y":137,"w":84,"h":62},"frame":{"x":968,"y":169,"w":84,"h":62}},"769/26_110":{"rotated":false,"trimmed":true,"sourceSize":{"w":400,"h":400},"spriteSourceSize":{"x":162,"y":151,"w":76,"h":48},"frame":{"x":157,"y":1,"w":76,"h":48}},"769/26_111":{"rotated":false,"trimmed":true,"sourceSize":{"w":400,"h":400},"spriteSourceSize":{"x":162,"y":151,"w":76,"h":48},"frame":{"x":157,"y":1,"w":76,"h":48}},"769/26_112":{"rotated":false,"trimmed":true,"sourceSize":{"w":400,"h":400},"spriteSourceSize":{"x":162,"y":151,"w":76,"h":48},"frame":{"x":157,"y":1,"w":76,"h":48}},"769/26_113":{"rotated":false,"trimmed":true,"sourceSize":{"w":400,"h":400},"spriteSourceSize":{"x":163,"y":160,"w":76,"h":49},"frame":{"x":771,"y":1,"w":76,"h":49}},"769/26_114":{"rotated":false,"trimmed":true,"sourceSize":{"w":400,"h":400},"spriteSourceSize":{"x":163,"y":160,"w":76,"h":49},"frame":{"x":771,"y":1,"w":76,"h":49}},"769/26_115":{"rotated":false,"trimmed":true,"sourceSize":{"w":400,"h":400},"spriteSourceSize":{"x":163,"y":160,"w":76,"h":49},"frame":{"x":771,"y":1,"w":76,"h":49}},"769/26_116":{"rotated":false,"trimmed":true,"sourceSize":{"w":400,"h":400},"spriteSourceSize":{"x":163,"y":160,"w":76,"h":49},"frame":{"x":771,"y":1,"w":76,"h":49}},"769/26_117":{"rotated":false,"trimmed":true,"sourceSize":{"w":400,"h":400},"spriteSourceSize":{"x":162,"y":151,"w":76,"h":48},"frame":{"x":157,"y":1,"w":76,"h":48}},"769/26_118":{"rotated":false,"trimmed":true,"sourceSize":{"w":400,"h":400},"spriteSourceSize":{"x":162,"y":151,"w":76,"h":48},"frame":{"x":157,"y":1,"w":76,"h":48}},"769/26_119":{"rotated":false,"trimmed":true,"sourceSize":{"w":400,"h":400},"spriteSourceSize":{"x":162,"y":151,"w":76,"h":48},"frame":{"x":157,"y":1,"w":76,"h":48}},"769/26_120":{"rotated":false,"trimmed":true,"sourceSize":{"w":400,"h":400},"spriteSourceSize":{"x":163,"y":160,"w":76,"h":49},"frame":{"x":771,"y":1,"w":76,"h":49}},"769/26_121":{"rotated":false,"trimmed":true,"sourceSize":{"w":400,"h":400},"spriteSourceSize":{"x":163,"y":160,"w":76,"h":49},"frame":{"x":771,"y":1,"w":76,"h":49}},"769/26_122":{"rotated":false,"trimmed":true,"sourceSize":{"w":400,"h":400},"spriteSourceSize":{"x":163,"y":160,"w":76,"h":49},"frame":{"x":771,"y":1,"w":76,"h":49}},"769/26_123":{"rotated":false,"trimmed":true,"sourceSize":{"w":400,"h":400},"spriteSourceSize":{"x":163,"y":160,"w":76,"h":49},"frame":{"x":771,"y":1,"w":76,"h":49}},"769/26_124":{"rotated":false,"trimmed":true,"sourceSize":{"w":400,"h":400},"spriteSourceSize":{"x":162,"y":151,"w":76,"h":48},"frame":{"x":157,"y":1,"w":76,"h":48}},"769/26_125":{"rotated":false,"trimmed":true,"sourceSize":{"w":400,"h":400},"spriteSourceSize":{"x":162,"y":151,"w":76,"h":48},"frame":{"x":157,"y":1,"w":76,"h":48}},"769/26_126":{"rotated":false,"trimmed":true,"sourceSize":{"w":400,"h":400},"spriteSourceSize":{"x":162,"y":151,"w":76,"h":48},"frame":{"x":157,"y":1,"w":76,"h":48}},"769/26_127":{"rotated":false,"trimmed":true,"sourceSize":{"w":400,"h":400},"spriteSourceSize":{"x":162,"y":151,"w":76,"h":48},"frame":{"x":235,"y":1,"w":76,"h":48}},"769/26_128":{"rotated":false,"trimmed":true,"sourceSize":{"w":400,"h":400},"spriteSourceSize":{"x":163,"y":150,"w":75,"h":49},"frame":{"x":849,"y":1,"w":75,"h":49}},"769/26_129":{"rotated":false,"trimmed":true,"sourceSize":{"w":400,"h":400},"spriteSourceSize":{"x":146,"y":148,"w":93,"h":51},"frame":{"x":1651,"y":1,"w":93,"h":51}},"769/26_130":{"rotated":false,"trimmed":true,"sourceSize":{"w":400,"h":400},"spriteSourceSize":{"x":145,"y":129,"w":96,"h":70},"frame":{"x":1793,"y":307,"w":96,"h":70}},"769/26_131":{"rotated":false,"trimmed":true,"sourceSize":{"w":400,"h":400},"spriteSourceSize":{"x":161,"y":136,"w":79,"h":63},"frame":{"x":82,"y":225,"w":79,"h":63}},"769/26_132":{"rotated":false,"trimmed":true,"sourceSize":{"w":400,"h":400},"spriteSourceSize":{"x":167,"y":135,"w":73,"h":64},"frame":{"x":654,"y":230,"w":73,"h":64}},"769/26_133":{"rotated":false,"trimmed":true,"sourceSize":{"w":400,"h":400},"spriteSourceSize":{"x":167,"y":135,"w":73,"h":64},"frame":{"x":654,"y":230,"w":73,"h":64}},"769/26_134":{"rotated":false,"trimmed":true,"sourceSize":{"w":400,"h":400},"spriteSourceSize":{"x":165,"y":135,"w":75,"h":64},"frame":{"x":729,"y":231,"w":75,"h":64}},"769/26_135":{"rotated":false,"trimmed":true,"sourceSize":{"w":400,"h":400},"spriteSourceSize":{"x":161,"y":136,"w":79,"h":63},"frame":{"x":163,"y":226,"w":79,"h":63}},"769/26_136":{"rotated":false,"trimmed":true,"sourceSize":{"w":400,"h":400},"spriteSourceSize":{"x":157,"y":137,"w":83,"h":62},"frame":{"x":1054,"y":171,"w":83,"h":62}},"769/26_137":{"rotated":false,"trimmed":true,"sourceSize":{"w":400,"h":400},"spriteSourceSize":{"x":157,"y":137,"w":83,"h":62},"frame":{"x":1054,"y":171,"w":83,"h":62}},"769/26_138":{"rotated":false,"trimmed":true,"sourceSize":{"w":400,"h":400},"spriteSourceSize":{"x":162,"y":151,"w":76,"h":48},"frame":{"x":157,"y":1,"w":76,"h":48}},"769/26_139":{"rotated":false,"trimmed":true,"sourceSize":{"w":400,"h":400},"spriteSourceSize":{"x":162,"y":151,"w":76,"h":48},"frame":{"x":157,"y":1,"w":76,"h":48}},"769/26_140":{"rotated":false,"trimmed":true,"sourceSize":{"w":400,"h":400},"spriteSourceSize":{"x":162,"y":151,"w":76,"h":48},"frame":{"x":157,"y":1,"w":76,"h":48}},"769/26_141":{"rotated":false,"trimmed":true,"sourceSize":{"w":400,"h":400},"spriteSourceSize":{"x":163,"y":160,"w":76,"h":49},"frame":{"x":771,"y":1,"w":76,"h":49}},"769/26_142":{"rotated":false,"trimmed":true,"sourceSize":{"w":400,"h":400},"spriteSourceSize":{"x":163,"y":160,"w":76,"h":49},"frame":{"x":771,"y":1,"w":76,"h":49}},"769/26_143":{"rotated":false,"trimmed":true,"sourceSize":{"w":400,"h":400},"spriteSourceSize":{"x":163,"y":160,"w":76,"h":49},"frame":{"x":771,"y":1,"w":76,"h":49}},"769/26_144":{"rotated":false,"trimmed":true,"sourceSize":{"w":400,"h":400},"spriteSourceSize":{"x":163,"y":160,"w":76,"h":49},"frame":{"x":771,"y":1,"w":76,"h":49}},"769/26_145":{"rotated":false,"trimmed":true,"sourceSize":{"w":400,"h":400},"spriteSourceSize":{"x":162,"y":151,"w":76,"h":48},"frame":{"x":157,"y":1,"w":76,"h":48}},"769/26_146":{"rotated":false,"trimmed":true,"sourceSize":{"w":400,"h":400},"spriteSourceSize":{"x":162,"y":151,"w":76,"h":48},"frame":{"x":157,"y":1,"w":76,"h":48}},"769/26_147":{"rotated":false,"trimmed":true,"sourceSize":{"w":400,"h":400},"spriteSourceSize":{"x":162,"y":151,"w":76,"h":48},"frame":{"x":157,"y":1,"w":76,"h":48}},"769/26_148":{"rotated":false,"trimmed":true,"sourceSize":{"w":400,"h":400},"spriteSourceSize":{"x":163,"y":160,"w":76,"h":49},"frame":{"x":771,"y":1,"w":76,"h":49}},"769/26_149":{"rotated":false,"trimmed":true,"sourceSize":{"w":400,"h":400},"spriteSourceSize":{"x":163,"y":160,"w":76,"h":49},"frame":{"x":771,"y":1,"w":76,"h":49}},"769/26_150":{"rotated":false,"trimmed":true,"sourceSize":{"w":400,"h":400},"spriteSourceSize":{"x":163,"y":160,"w":76,"h":49},"frame":{"x":771,"y":1,"w":76,"h":49}},"769/26_151":{"rotated":false,"trimmed":true,"sourceSize":{"w":400,"h":400},"spriteSourceSize":{"x":163,"y":160,"w":76,"h":49},"frame":{"x":771,"y":1,"w":76,"h":49}},"769/26_152":{"rotated":false,"trimmed":true,"sourceSize":{"w":400,"h":400},"spriteSourceSize":{"x":162,"y":151,"w":76,"h":48},"frame":{"x":157,"y":1,"w":76,"h":48}},"769/26_153":{"rotated":false,"trimmed":true,"sourceSize":{"w":400,"h":400},"spriteSourceSize":{"x":162,"y":151,"w":76,"h":48},"frame":{"x":157,"y":1,"w":76,"h":48}},"769/26_154":{"rotated":false,"trimmed":true,"sourceSize":{"w":400,"h":400},"spriteSourceSize":{"x":162,"y":151,"w":76,"h":48},"frame":{"x":157,"y":1,"w":76,"h":48}},"769/26_155":{"rotated":false,"trimmed":true,"sourceSize":{"w":400,"h":400},"spriteSourceSize":{"x":166,"y":142,"w":59,"h":69},"frame":{"x":562,"y":295,"w":59,"h":69}},"769/26_156":{"rotated":false,"trimmed":true,"sourceSize":{"w":400,"h":400},"spriteSourceSize":{"x":175,"y":149,"w":57,"h":73},"frame":{"x":827,"y":370,"w":57,"h":73}},"769/26_157":{"rotated":false,"trimmed":true,"sourceSize":{"w":400,"h":400},"spriteSourceSize":{"x":178,"y":159,"w":64,"h":75},"frame":{"x":1415,"y":377,"w":64,"h":75}},"769/26_158":{"rotated":false,"trimmed":true,"sourceSize":{"w":400,"h":400},"spriteSourceSize":{"x":183,"y":167,"w":67,"h":72},"frame":{"x":622,"y":368,"w":67,"h":72}},"769/26_159":{"rotated":false,"trimmed":true,"sourceSize":{"w":400,"h":400},"spriteSourceSize":{"x":183,"y":167,"w":67,"h":72},"frame":{"x":622,"y":368,"w":67,"h":72}},"769/26_160":{"rotated":false,"trimmed":true,"sourceSize":{"w":400,"h":400},"spriteSourceSize":{"x":183,"y":167,"w":67,"h":72},"frame":{"x":622,"y":368,"w":67,"h":72}},"769/26_161":{"rotated":false,"trimmed":true,"sourceSize":{"w":400,"h":400},"spriteSourceSize":{"x":183,"y":167,"w":67,"h":72},"frame":{"x":622,"y":368,"w":67,"h":72}},"769/26_162":{"rotated":false,"trimmed":true,"sourceSize":{"w":400,"h":400},"spriteSourceSize":{"x":178,"y":159,"w":64,"h":75},"frame":{"x":1415,"y":377,"w":64,"h":75}},"769/26_163":{"rotated":false,"trimmed":true,"sourceSize":{"w":400,"h":400},"spriteSourceSize":{"x":175,"y":149,"w":57,"h":73},"frame":{"x":827,"y":370,"w":57,"h":73}},"769/26_164":{"rotated":false,"trimmed":true,"sourceSize":{"w":400,"h":400},"spriteSourceSize":{"x":166,"y":142,"w":59,"h":69},"frame":{"x":562,"y":295,"w":59,"h":69}},"769/26_165":{"rotated":false,"trimmed":true,"sourceSize":{"w":400,"h":400},"spriteSourceSize":{"x":166,"y":142,"w":59,"h":69},"frame":{"x":562,"y":295,"w":59,"h":69}},"769/26_166":{"rotated":false,"trimmed":true,"sourceSize":{"w":400,"h":400},"spriteSourceSize":{"x":162,"y":151,"w":76,"h":48},"frame":{"x":157,"y":1,"w":76,"h":48}},"769/26_167":{"rotated":false,"trimmed":true,"sourceSize":{"w":400,"h":400},"spriteSourceSize":{"x":162,"y":151,"w":76,"h":48},"frame":{"x":157,"y":1,"w":76,"h":48}},"769/26_168":{"rotated":false,"trimmed":true,"sourceSize":{"w":400,"h":400},"spriteSourceSize":{"x":162,"y":151,"w":76,"h":48},"frame":{"x":157,"y":1,"w":76,"h":48}},"769/26_169":{"rotated":false,"trimmed":true,"sourceSize":{"w":400,"h":400},"spriteSourceSize":{"x":163,"y":160,"w":76,"h":49},"frame":{"x":771,"y":1,"w":76,"h":49}},"769/26_170":{"rotated":false,"trimmed":true,"sourceSize":{"w":400,"h":400},"spriteSourceSize":{"x":163,"y":160,"w":76,"h":49},"frame":{"x":771,"y":1,"w":76,"h":49}},"769/26_171":{"rotated":false,"trimmed":true,"sourceSize":{"w":400,"h":400},"spriteSourceSize":{"x":163,"y":160,"w":76,"h":49},"frame":{"x":771,"y":1,"w":76,"h":49}},"769/26_172":{"rotated":false,"trimmed":true,"sourceSize":{"w":400,"h":400},"spriteSourceSize":{"x":163,"y":160,"w":76,"h":49},"frame":{"x":771,"y":1,"w":76,"h":49}},"769/26_173":{"rotated":false,"trimmed":true,"sourceSize":{"w":400,"h":400},"spriteSourceSize":{"x":162,"y":151,"w":76,"h":48},"frame":{"x":157,"y":1,"w":76,"h":48}},"769/26_174":{"rotated":false,"trimmed":true,"sourceSize":{"w":400,"h":400},"spriteSourceSize":{"x":162,"y":151,"w":76,"h":48},"frame":{"x":157,"y":1,"w":76,"h":48}},"769/26_175":{"rotated":false,"trimmed":true,"sourceSize":{"w":400,"h":400},"spriteSourceSize":{"x":162,"y":151,"w":76,"h":48},"frame":{"x":157,"y":1,"w":76,"h":48}},"769/26_176":{"rotated":false,"trimmed":true,"sourceSize":{"w":400,"h":400},"spriteSourceSize":{"x":163,"y":160,"w":76,"h":49},"frame":{"x":771,"y":1,"w":76,"h":49}},"769/26_177":{"rotated":false,"trimmed":true,"sourceSize":{"w":400,"h":400},"spriteSourceSize":{"x":163,"y":160,"w":76,"h":49},"frame":{"x":771,"y":1,"w":76,"h":49}},"769/26_178":{"rotated":false,"trimmed":true,"sourceSize":{"w":400,"h":400},"spriteSourceSize":{"x":163,"y":160,"w":76,"h":49},"frame":{"x":771,"y":1,"w":76,"h":49}},"769/26_179":{"rotated":false,"trimmed":true,"sourceSize":{"w":400,"h":400},"spriteSourceSize":{"x":163,"y":160,"w":76,"h":49},"frame":{"x":771,"y":1,"w":76,"h":49}},"769/26_180":{"rotated":false,"trimmed":true,"sourceSize":{"w":400,"h":400},"spriteSourceSize":{"x":162,"y":151,"w":76,"h":48},"frame":{"x":157,"y":1,"w":76,"h":48}},"769/26_181":{"rotated":false,"trimmed":true,"sourceSize":{"w":400,"h":400},"spriteSourceSize":{"x":162,"y":151,"w":76,"h":48},"frame":{"x":157,"y":1,"w":76,"h":48}},"769/26_182":{"rotated":false,"trimmed":true,"sourceSize":{"w":400,"h":400},"spriteSourceSize":{"x":162,"y":151,"w":76,"h":48},"frame":{"x":157,"y":1,"w":76,"h":48}},"769/26_183":{"rotated":false,"trimmed":true,"sourceSize":{"w":400,"h":400},"spriteSourceSize":{"x":178,"y":142,"w":58,"h":69},"frame":{"x":623,"y":296,"w":58,"h":69}},"769/26_184":{"rotated":false,"trimmed":true,"sourceSize":{"w":400,"h":400},"spriteSourceSize":{"x":170,"y":150,"w":58,"h":73},"frame":{"x":886,"y":371,"w":58,"h":73}},"769/26_185":{"rotated":false,"trimmed":true,"sourceSize":{"w":400,"h":400},"spriteSourceSize":{"x":161,"y":159,"w":63,"h":75},"frame":{"x":1481,"y":378,"w":63,"h":75}},"769/26_186":{"rotated":false,"trimmed":true,"sourceSize":{"w":400,"h":400},"spriteSourceSize":{"x":153,"y":167,"w":66,"h":72},"frame":{"x":691,"y":368,"w":66,"h":72}},"769/26_187":{"rotated":false,"trimmed":true,"sourceSize":{"w":400,"h":400},"spriteSourceSize":{"x":153,"y":167,"w":66,"h":72},"frame":{"x":691,"y":368,"w":66,"h":72}},"769/26_188":{"rotated":false,"trimmed":true,"sourceSize":{"w":400,"h":400},"spriteSourceSize":{"x":153,"y":167,"w":66,"h":72},"frame":{"x":691,"y":368,"w":66,"h":72}},"769/26_189":{"rotated":false,"trimmed":true,"sourceSize":{"w":400,"h":400},"spriteSourceSize":{"x":153,"y":167,"w":66,"h":72},"frame":{"x":691,"y":368,"w":66,"h":72}},"769/26_190":{"rotated":false,"trimmed":true,"sourceSize":{"w":400,"h":400},"spriteSourceSize":{"x":161,"y":159,"w":63,"h":74},"frame":{"x":1066,"y":374,"w":63,"h":74}},"769/26_191":{"rotated":false,"trimmed":true,"sourceSize":{"w":400,"h":400},"spriteSourceSize":{"x":170,"y":149,"w":58,"h":73},"frame":{"x":946,"y":373,"w":58,"h":73}},"769/26_192":{"rotated":false,"trimmed":true,"sourceSize":{"w":400,"h":400},"spriteSourceSize":{"x":178,"y":142,"w":58,"h":69},"frame":{"x":744,"y":297,"w":58,"h":69}},"769/26_193":{"rotated":false,"trimmed":true,"sourceSize":{"w":400,"h":400},"spriteSourceSize":{"x":178,"y":142,"w":58,"h":69},"frame":{"x":744,"y":297,"w":58,"h":69}},"769/27_1":{"rotated":false,"trimmed":true,"sourceSize":{"w":400,"h":400},"spriteSourceSize":{"x":176,"y":141,"w":58,"h":69},"frame":{"x":864,"y":299,"w":58,"h":69}},"769/27_2":{"rotated":false,"trimmed":true,"sourceSize":{"w":400,"h":400},"spriteSourceSize":{"x":168,"y":148,"w":58,"h":73},"frame":{"x":1006,"y":374,"w":58,"h":73}},"769/27_3":{"rotated":false,"trimmed":true,"sourceSize":{"w":400,"h":400},"spriteSourceSize":{"x":159,"y":158,"w":63,"h":75},"frame":{"x":1546,"y":378,"w":63,"h":75}},"769/27_4":{"rotated":false,"trimmed":true,"sourceSize":{"w":400,"h":400},"spriteSourceSize":{"x":151,"y":166,"w":66,"h":72},"frame":{"x":759,"y":368,"w":66,"h":72}},"769/27_5":{"rotated":false,"trimmed":true,"sourceSize":{"w":400,"h":400},"spriteSourceSize":{"x":151,"y":166,"w":65,"h":71},"frame":{"x":244,"y":363,"w":65,"h":71}},"769/27_6":{"rotated":false,"trimmed":true,"sourceSize":{"w":400,"h":400},"spriteSourceSize":{"x":153,"y":165,"w":62,"h":62},"frame":{"x":1212,"y":172,"w":62,"h":62}},"769/27_7":{"rotated":false,"trimmed":true,"sourceSize":{"w":400,"h":400},"spriteSourceSize":{"x":153,"y":165,"w":62,"h":57},"frame":{"x":469,"y":106,"w":62,"h":57}},"769/27_8":{"rotated":false,"trimmed":true,"sourceSize":{"w":400,"h":400},"spriteSourceSize":{"x":152,"y":165,"w":63,"h":52},"frame":{"x":579,"y":52,"w":63,"h":52}},"769/27_9":{"rotated":false,"trimmed":true,"sourceSize":{"w":400,"h":400},"spriteSourceSize":{"x":152,"y":165,"w":63,"h":52},"frame":{"x":579,"y":52,"w":63,"h":52}},"769/27_10":{"rotated":false,"trimmed":true,"sourceSize":{"w":400,"h":400},"spriteSourceSize":{"x":153,"y":165,"w":62,"h":52},"frame":{"x":515,"y":52,"w":62,"h":52}},"769/27_11":{"rotated":false,"trimmed":true,"sourceSize":{"w":400,"h":400},"spriteSourceSize":{"x":153,"y":165,"w":62,"h":52},"frame":{"x":515,"y":52,"w":62,"h":52}},"769/27_12":{"rotated":false,"trimmed":true,"sourceSize":{"w":400,"h":400},"spriteSourceSize":{"x":153,"y":165,"w":62,"h":52},"frame":{"x":515,"y":52,"w":62,"h":52}},"769/27_13":{"rotated":false,"trimmed":true,"sourceSize":{"w":400,"h":400},"spriteSourceSize":{"x":157,"y":163,"w":63,"h":59},"frame":{"x":1321,"y":111,"w":63,"h":59}},"769/27_14":{"rotated":false,"trimmed":true,"sourceSize":{"w":400,"h":400},"spriteSourceSize":{"x":161,"y":159,"w":63,"h":67},"frame":{"x":1488,"y":236,"w":63,"h":67}},"769/27_15":{"rotated":false,"trimmed":true,"sourceSize":{"w":400,"h":400},"spriteSourceSize":{"x":169,"y":154,"w":61,"h":69},"frame":{"x":924,"y":300,"w":61,"h":69}},"769/27_16":{"rotated":false,"trimmed":true,"sourceSize":{"w":400,"h":400},"spriteSourceSize":{"x":177,"y":147,"w":60,"h":58},"frame":{"x":863,"y":107,"w":60,"h":58}},"769/27_17":{"rotated":false,"trimmed":true,"sourceSize":{"w":400,"h":400},"spriteSourceSize":{"x":175,"y":147,"w":75,"h":50},"frame":{"x":1075,"y":1,"w":75,"h":50}},"769/27_18":{"rotated":false,"trimmed":true,"sourceSize":{"w":400,"h":400},"spriteSourceSize":{"x":173,"y":122,"w":87,"h":74},"frame":{"x":1131,"y":374,"w":87,"h":74}},"769/27_19":{"rotated":false,"trimmed":true,"sourceSize":{"w":400,"h":400},"spriteSourceSize":{"x":171,"y":129,"w":91,"h":68},"frame":{"x":66,"y":290,"w":91,"h":68}},"769/27_20":{"rotated":false,"trimmed":true,"sourceSize":{"w":400,"h":400},"spriteSourceSize":{"x":170,"y":136,"w":92,"h":63},"frame":{"x":244,"y":226,"w":92,"h":63}},"769/27_21":{"rotated":false,"trimmed":true,"sourceSize":{"w":400,"h":400},"spriteSourceSize":{"x":173,"y":144,"w":58,"h":57},"frame":{"x":409,"y":106,"w":58,"h":57}},"769/27_22":{"rotated":false,"trimmed":true,"sourceSize":{"w":400,"h":400},"spriteSourceSize":{"x":158,"y":143,"w":71,"h":62},"frame":{"x":1139,"y":172,"w":71,"h":62}},"769/27_23":{"rotated":false,"trimmed":true,"sourceSize":{"w":400,"h":400},"spriteSourceSize":{"x":165,"y":144,"w":62,"h":68},"frame":{"x":159,"y":291,"w":62,"h":68}},"769/27_24":{"rotated":false,"trimmed":true,"sourceSize":{"w":400,"h":400},"spriteSourceSize":{"x":173,"y":145,"w":53,"h":79},"frame":{"x":494,"y":438,"w":53,"h":79}},"769/27_25":{"rotated":false,"trimmed":true,"sourceSize":{"w":400,"h":400},"spriteSourceSize":{"x":175,"y":143,"w":53,"h":78},"frame":{"x":1,"y":431,"w":53,"h":78}},"769/27_26":{"rotated":false,"trimmed":true,"sourceSize":{"w":400,"h":400},"spriteSourceSize":{"x":175,"y":142,"w":58,"h":69},"frame":{"x":987,"y":302,"w":58,"h":69}},"769/27_27":{"rotated":false,"trimmed":true,"sourceSize":{"w":400,"h":400},"spriteSourceSize":{"x":175,"y":142,"w":59,"h":69},"frame":{"x":1047,"y":303,"w":59,"h":69}},"769/27_28":{"rotated":false,"trimmed":true,"sourceSize":{"w":400,"h":400},"spriteSourceSize":{"x":176,"y":142,"w":58,"h":68},"frame":{"x":223,"y":291,"w":58,"h":68}},"769/28_1":{"rotated":false,"trimmed":true,"sourceSize":{"w":400,"h":400},"spriteSourceSize":{"x":174,"y":147,"w":59,"h":71},"frame":{"x":311,"y":363,"w":59,"h":71}},"769/28_2":{"rotated":false,"trimmed":true,"sourceSize":{"w":400,"h":400},"spriteSourceSize":{"x":163,"y":142,"w":66,"h":67},"frame":{"x":1716,"y":238,"w":66,"h":67}},"769/28_3":{"rotated":false,"trimmed":true,"sourceSize":{"w":400,"h":400},"spriteSourceSize":{"x":155,"y":139,"w":70,"h":64},"frame":{"x":806,"y":231,"w":70,"h":64}},"769/28_4":{"rotated":false,"trimmed":true,"sourceSize":{"w":400,"h":400},"spriteSourceSize":{"x":156,"y":138,"w":67,"h":60},"frame":{"x":1961,"y":123,"w":67,"h":60}},"769/28_5":{"rotated":false,"trimmed":true,"sourceSize":{"w":400,"h":400},"spriteSourceSize":{"x":158,"y":138,"w":64,"h":59},"frame":{"x":1386,"y":111,"w":64,"h":59}},"769/28_6":{"rotated":false,"trimmed":true,"sourceSize":{"w":400,"h":400},"spriteSourceSize":{"x":160,"y":140,"w":63,"h":56},"frame":{"x":221,"y":105,"w":63,"h":56}},"769/28_7":{"rotated":false,"trimmed":true,"sourceSize":{"w":400,"h":400},"spriteSourceSize":{"x":162,"y":141,"w":61,"h":55},"frame":{"x":1655,"y":54,"w":61,"h":55}},"769/28_8":{"rotated":false,"trimmed":true,"sourceSize":{"w":400,"h":400},"spriteSourceSize":{"x":164,"y":141,"w":59,"h":55},"frame":{"x":1594,"y":54,"w":59,"h":55}},"769/28_9":{"rotated":false,"trimmed":true,"sourceSize":{"w":400,"h":400},"spriteSourceSize":{"x":164,"y":141,"w":59,"h":55},"frame":{"x":1594,"y":54,"w":59,"h":55}},"769/28_10":{"rotated":false,"trimmed":true,"sourceSize":{"w":400,"h":400},"spriteSourceSize":{"x":164,"y":141,"w":59,"h":55},"frame":{"x":1594,"y":54,"w":59,"h":55}},"769/28_11":{"rotated":false,"trimmed":true,"sourceSize":{"w":400,"h":400},"spriteSourceSize":{"x":164,"y":141,"w":59,"h":55},"frame":{"x":1594,"y":54,"w":59,"h":55}},"769/28_12":{"rotated":false,"trimmed":true,"sourceSize":{"w":400,"h":400},"spriteSourceSize":{"x":164,"y":141,"w":59,"h":55},"frame":{"x":1594,"y":54,"w":59,"h":55}},"769/28_13":{"rotated":false,"trimmed":true,"sourceSize":{"w":400,"h":400},"spriteSourceSize":{"x":162,"y":142,"w":61,"h":58},"frame":{"x":925,"y":109,"w":61,"h":58}},"769/28_14":{"rotated":false,"trimmed":true,"sourceSize":{"w":400,"h":400},"spriteSourceSize":{"x":163,"y":143,"w":61,"h":61},"frame":{"x":474,"y":165,"w":61,"h":61}},"769/28_15":{"rotated":false,"trimmed":true,"sourceSize":{"w":400,"h":400},"spriteSourceSize":{"x":156,"y":145,"w":70,"h":65},"frame":{"x":1137,"y":236,"w":70,"h":65}},"769/28_16":{"rotated":false,"trimmed":true,"sourceSize":{"w":400,"h":400},"spriteSourceSize":{"x":153,"y":148,"w":75,"h":66},"frame":{"x":1281,"y":236,"w":75,"h":66}},"769/28_17":{"rotated":false,"trimmed":true,"sourceSize":{"w":400,"h":400},"spriteSourceSize":{"x":161,"y":147,"w":68,"h":67},"frame":{"x":1553,"y":237,"w":68,"h":67}},"769/28_18":{"rotated":false,"trimmed":true,"sourceSize":{"w":400,"h":400},"spriteSourceSize":{"x":186,"y":147,"w":44,"h":67},"frame":{"x":1994,"y":54,"w":44,"h":67}},"769/28_19":{"rotated":false,"trimmed":true,"sourceSize":{"w":400,"h":400},"spriteSourceSize":{"x":184,"y":147,"w":45,"h":67},"frame":{"x":1623,"y":237,"w":45,"h":67}},"769/28_20":{"rotated":false,"trimmed":true,"sourceSize":{"w":400,"h":400},"spriteSourceSize":{"x":179,"y":147,"w":51,"h":66},"frame":{"x":1084,"y":235,"w":51,"h":66}},"769/28_21":{"rotated":false,"trimmed":true,"sourceSize":{"w":400,"h":400},"spriteSourceSize":{"x":159,"y":131,"w":72,"h":81},"frame":{"x":988,"y":449,"w":72,"h":81}},"769/28_22":{"rotated":false,"trimmed":true,"sourceSize":{"w":400,"h":400},"spriteSourceSize":{"x":170,"y":131,"w":65,"h":78},"frame":{"x":56,"y":432,"w":65,"h":78}},"769/28_23":{"rotated":false,"trimmed":true,"sourceSize":{"w":400,"h":400},"spriteSourceSize":{"x":162,"y":147,"w":72,"h":61},"frame":{"x":537,"y":165,"w":72,"h":61}},"769/28_24":{"rotated":false,"trimmed":true,"sourceSize":{"w":400,"h":400},"spriteSourceSize":{"x":159,"y":145,"w":74,"h":62},"frame":{"x":1276,"y":172,"w":74,"h":62}},"769/28_25":{"rotated":false,"trimmed":true,"sourceSize":{"w":400,"h":400},"spriteSourceSize":{"x":164,"y":145,"w":69,"h":63},"frame":{"x":1960,"y":185,"w":69,"h":63}},"769/28_26":{"rotated":false,"trimmed":true,"sourceSize":{"w":400,"h":400},"spriteSourceSize":{"x":174,"y":146,"w":59,"h":70},"frame":{"x":1475,"y":305,"w":59,"h":70}},"769/28_27":{"rotated":false,"trimmed":true,"sourceSize":{"w":400,"h":400},"spriteSourceSize":{"x":174,"y":146,"w":59,"h":71},"frame":{"x":372,"y":363,"w":59,"h":71}},"769/28_28":{"rotated":false,"trimmed":true,"sourceSize":{"w":400,"h":400},"spriteSourceSize":{"x":174,"y":147,"w":59,"h":70},"frame":{"x":1634,"y":306,"w":59,"h":70}},"769/29_1":{"rotated":false,"trimmed":true,"sourceSize":{"w":400,"h":400},"spriteSourceSize":{"x":168,"y":147,"w":59,"h":71},"frame":{"x":433,"y":363,"w":59,"h":71}},"769/29_2":{"rotated":false,"trimmed":true,"sourceSize":{"w":400,"h":400},"spriteSourceSize":{"x":172,"y":142,"w":66,"h":67},"frame":{"x":1960,"y":250,"w":66,"h":67}},"769/29_3":{"rotated":false,"trimmed":true,"sourceSize":{"w":400,"h":400},"spriteSourceSize":{"x":176,"y":139,"w":70,"h":64},"frame":{"x":878,"y":233,"w":70,"h":64}},"769/29_4":{"rotated":false,"trimmed":true,"sourceSize":{"w":400,"h":400},"spriteSourceSize":{"x":178,"y":138,"w":67,"h":60},"frame":{"x":1,"y":162,"w":67,"h":60}},"769/29_5":{"rotated":false,"trimmed":true,"sourceSize":{"w":400,"h":400},"spriteSourceSize":{"x":179,"y":138,"w":64,"h":59},"frame":{"x":1452,"y":111,"w":64,"h":59}},"769/29_6":{"rotated":false,"trimmed":true,"sourceSize":{"w":400,"h":400},"spriteSourceSize":{"x":178,"y":140,"w":63,"h":56},"frame":{"x":286,"y":105,"w":63,"h":56}},"769/29_7":{"rotated":false,"trimmed":true,"sourceSize":{"w":400,"h":400},"spriteSourceSize":{"x":178,"y":141,"w":61,"h":55},"frame":{"x":1779,"y":54,"w":61,"h":55}},"769/29_8":{"rotated":false,"trimmed":true,"sourceSize":{"w":400,"h":400},"spriteSourceSize":{"x":178,"y":141,"w":59,"h":55},"frame":{"x":1718,"y":54,"w":59,"h":55}},"769/29_9":{"rotated":false,"trimmed":true,"sourceSize":{"w":400,"h":400},"spriteSourceSize":{"x":178,"y":141,"w":59,"h":55},"frame":{"x":1718,"y":54,"w":59,"h":55}},"769/29_10":{"rotated":false,"trimmed":true,"sourceSize":{"w":400,"h":400},"spriteSourceSize":{"x":178,"y":141,"w":59,"h":55},"frame":{"x":1718,"y":54,"w":59,"h":55}},"769/29_11":{"rotated":false,"trimmed":true,"sourceSize":{"w":400,"h":400},"spriteSourceSize":{"x":178,"y":141,"w":59,"h":55},"frame":{"x":1718,"y":54,"w":59,"h":55}},"769/29_12":{"rotated":false,"trimmed":true,"sourceSize":{"w":400,"h":400},"spriteSourceSize":{"x":178,"y":141,"w":59,"h":55},"frame":{"x":1718,"y":54,"w":59,"h":55}},"769/29_13":{"rotated":false,"trimmed":true,"sourceSize":{"w":400,"h":400},"spriteSourceSize":{"x":178,"y":142,"w":61,"h":58},"frame":{"x":988,"y":109,"w":61,"h":58}},"769/29_14":{"rotated":false,"trimmed":true,"sourceSize":{"w":400,"h":400},"spriteSourceSize":{"x":177,"y":143,"w":61,"h":61},"frame":{"x":611,"y":166,"w":61,"h":61}},"769/29_15":{"rotated":false,"trimmed":true,"sourceSize":{"w":400,"h":400},"spriteSourceSize":{"x":175,"y":145,"w":70,"h":65},"frame":{"x":1209,"y":236,"w":70,"h":65}},"769/29_16":{"rotated":false,"trimmed":true,"sourceSize":{"w":400,"h":400},"spriteSourceSize":{"x":173,"y":148,"w":75,"h":66},"frame":{"x":1358,"y":236,"w":75,"h":66}},"769/29_17":{"rotated":false,"trimmed":true,"sourceSize":{"w":400,"h":400},"spriteSourceSize":{"x":172,"y":147,"w":68,"h":67},"frame":{"x":1784,"y":238,"w":68,"h":67}},"769/29_18":{"rotated":false,"trimmed":true,"sourceSize":{"w":400,"h":400},"spriteSourceSize":{"x":171,"y":147,"w":44,"h":67},"frame":{"x":1670,"y":237,"w":44,"h":67}},"769/29_19":{"rotated":false,"trimmed":true,"sourceSize":{"w":400,"h":400},"spriteSourceSize":{"x":172,"y":147,"w":45,"h":67},"frame":{"x":1854,"y":238,"w":45,"h":67}},"769/29_20":{"rotated":false,"trimmed":true,"sourceSize":{"w":400,"h":400},"spriteSourceSize":{"x":171,"y":147,"w":51,"h":66},"frame":{"x":1435,"y":236,"w":51,"h":66}},"769/29_21":{"rotated":false,"trimmed":true,"sourceSize":{"w":400,"h":400},"spriteSourceSize":{"x":170,"y":131,"w":72,"h":81},"frame":{"x":1062,"y":450,"w":72,"h":81}},"769/29_22":{"rotated":false,"trimmed":true,"sourceSize":{"w":400,"h":400},"spriteSourceSize":{"x":166,"y":131,"w":65,"h":78},"frame":{"x":123,"y":434,"w":65,"h":78}},"769/29_23":{"rotated":false,"trimmed":true,"sourceSize":{"w":400,"h":400},"spriteSourceSize":{"x":167,"y":147,"w":72,"h":61},"frame":{"x":674,"y":167,"w":72,"h":61}},"769/29_24":{"rotated":false,"trimmed":true,"sourceSize":{"w":400,"h":400},"spriteSourceSize":{"x":168,"y":145,"w":74,"h":62},"frame":{"x":1352,"y":172,"w":74,"h":62}},"769/29_25":{"rotated":false,"trimmed":true,"sourceSize":{"w":400,"h":400},"spriteSourceSize":{"x":168,"y":145,"w":69,"h":63},"frame":{"x":338,"y":228,"w":69,"h":63}},"769/29_26":{"rotated":false,"trimmed":true,"sourceSize":{"w":400,"h":400},"spriteSourceSize":{"x":168,"y":146,"w":59,"h":70},"frame":{"x":1891,"y":309,"w":59,"h":70}},"769/29_27":{"rotated":false,"trimmed":true,"sourceSize":{"w":400,"h":400},"spriteSourceSize":{"x":168,"y":146,"w":59,"h":71},"frame":{"x":494,"y":365,"w":59,"h":71}},"769/29_28":{"rotated":false,"trimmed":true,"sourceSize":{"w":400,"h":400},"spriteSourceSize":{"x":168,"y":147,"w":59,"h":70},"frame":{"x":1952,"y":319,"w":59,"h":70}},"769/30_1":{"rotated":false,"trimmed":true,"sourceSize":{"w":400,"h":400},"spriteSourceSize":{"x":164,"y":141,"w":59,"h":69},"frame":{"x":562,"y":295,"w":59,"h":69}},"769/30_2":{"rotated":false,"trimmed":true,"sourceSize":{"w":400,"h":400},"spriteSourceSize":{"x":173,"y":148,"w":57,"h":73},"frame":{"x":827,"y":370,"w":57,"h":73}},"769/30_3":{"rotated":false,"trimmed":true,"sourceSize":{"w":400,"h":400},"spriteSourceSize":{"x":176,"y":158,"w":64,"h":75},"frame":{"x":1415,"y":377,"w":64,"h":75}},"769/30_4":{"rotated":false,"trimmed":true,"sourceSize":{"w":400,"h":400},"spriteSourceSize":{"x":181,"y":166,"w":67,"h":72},"frame":{"x":622,"y":368,"w":67,"h":72}},"769/30_5":{"rotated":false,"trimmed":true,"sourceSize":{"w":400,"h":400},"spriteSourceSize":{"x":182,"y":166,"w":65,"h":71},"frame":{"x":555,"y":366,"w":65,"h":71}},"769/30_6":{"rotated":false,"trimmed":true,"sourceSize":{"w":400,"h":400},"spriteSourceSize":{"x":183,"y":165,"w":63,"h":62},"frame":{"x":1500,"y":172,"w":63,"h":62}},"769/30_7":{"rotated":false,"trimmed":true,"sourceSize":{"w":400,"h":400},"spriteSourceSize":{"x":183,"y":165,"w":62,"h":57},"frame":{"x":592,"y":106,"w":62,"h":57}},"769/30_8":{"rotated":false,"trimmed":true,"sourceSize":{"w":400,"h":400},"spriteSourceSize":{"x":183,"y":165,"w":63,"h":52},"frame":{"x":709,"y":52,"w":63,"h":52}},"769/30_9":{"rotated":false,"trimmed":true,"sourceSize":{"w":400,"h":400},"spriteSourceSize":{"x":183,"y":165,"w":63,"h":52},"frame":{"x":709,"y":52,"w":63,"h":52}},"769/30_10":{"rotated":false,"trimmed":true,"sourceSize":{"w":400,"h":400},"spriteSourceSize":{"x":183,"y":165,"w":63,"h":52},"frame":{"x":644,"y":52,"w":63,"h":52}},"769/30_11":{"rotated":false,"trimmed":true,"sourceSize":{"w":400,"h":400},"spriteSourceSize":{"x":183,"y":165,"w":63,"h":52},"frame":{"x":644,"y":52,"w":63,"h":52}},"769/30_12":{"rotated":false,"trimmed":true,"sourceSize":{"w":400,"h":400},"spriteSourceSize":{"x":183,"y":165,"w":63,"h":52},"frame":{"x":644,"y":52,"w":63,"h":52}},"769/30_13":{"rotated":false,"trimmed":true,"sourceSize":{"w":400,"h":400},"spriteSourceSize":{"x":178,"y":163,"w":64,"h":59},"frame":{"x":1518,"y":111,"w":64,"h":59}},"769/30_14":{"rotated":false,"trimmed":true,"sourceSize":{"w":400,"h":400},"spriteSourceSize":{"x":175,"y":159,"w":63,"h":67},"frame":{"x":1,"y":290,"w":63,"h":67}},"769/30_15":{"rotated":false,"trimmed":true,"sourceSize":{"w":400,"h":400},"spriteSourceSize":{"x":169,"y":154,"w":61,"h":69},"frame":{"x":1108,"y":303,"w":61,"h":69}},"769/30_16":{"rotated":false,"trimmed":true,"sourceSize":{"w":400,"h":400},"spriteSourceSize":{"x":162,"y":147,"w":60,"h":58},"frame":{"x":1051,"y":109,"w":60,"h":58}},"769/30_17":{"rotated":false,"trimmed":true,"sourceSize":{"w":400,"h":400},"spriteSourceSize":{"x":148,"y":147,"w":75,"h":50},"frame":{"x":1152,"y":1,"w":75,"h":50}},"769/30_18":{"rotated":false,"trimmed":true,"sourceSize":{"w":400,"h":400},"spriteSourceSize":{"x":138,"y":122,"w":87,"h":74},"frame":{"x":1273,"y":376,"w":87,"h":74}},"769/30_19":{"rotated":false,"trimmed":true,"sourceSize":{"w":400,"h":400},"spriteSourceSize":{"x":137,"y":129,"w":91,"h":68},"frame":{"x":283,"y":293,"w":91,"h":68}},"769/30_20":{"rotated":false,"trimmed":true,"sourceSize":{"w":400,"h":400},"spriteSourceSize":{"x":137,"y":136,"w":91,"h":63},"frame":{"x":409,"y":228,"w":91,"h":63}},"769/30_21":{"rotated":false,"trimmed":true,"sourceSize":{"w":400,"h":400},"spriteSourceSize":{"x":168,"y":144,"w":57,"h":57},"frame":{"x":533,"y":106,"w":57,"h":57}},"769/30_22":{"rotated":false,"trimmed":true,"sourceSize":{"w":400,"h":400},"spriteSourceSize":{"x":170,"y":143,"w":70,"h":62},"frame":{"x":1428,"y":172,"w":70,"h":62}},"769/30_23":{"rotated":false,"trimmed":true,"sourceSize":{"w":400,"h":400},"spriteSourceSize":{"x":171,"y":144,"w":63,"h":68},"frame":{"x":376,"y":293,"w":63,"h":68}},"769/30_24":{"rotated":false,"trimmed":true,"sourceSize":{"w":400,"h":400},"spriteSourceSize":{"x":172,"y":145,"w":53,"h":79},"frame":{"x":549,"y":439,"w":53,"h":79}},"769/30_25":{"rotated":false,"trimmed":true,"sourceSize":{"w":400,"h":400},"spriteSourceSize":{"x":171,"y":143,"w":53,"h":78},"frame":{"x":240,"y":436,"w":53,"h":78}},"769/30_26":{"rotated":false,"trimmed":true,"sourceSize":{"w":400,"h":400},"spriteSourceSize":{"x":166,"y":142,"w":57,"h":69},"frame":{"x":1901,"y":238,"w":57,"h":69}},"769/30_27":{"rotated":false,"trimmed":true,"sourceSize":{"w":400,"h":400},"spriteSourceSize":{"x":164,"y":142,"w":59,"h":69},"frame":{"x":1171,"y":303,"w":59,"h":69}},"769/30_28":{"rotated":false,"trimmed":true,"sourceSize":{"w":400,"h":400},"spriteSourceSize":{"x":164,"y":142,"w":59,"h":68},"frame":{"x":441,"y":293,"w":59,"h":68}}}}